[
    {
        "geo": {
            "place_id": "fe4b2b8e51cc85c1"
        },
        "id": "1527675610788765696",
        "text": "Biggggg congrats to my sister for passing the Georgia Bar \ud83e\udd73\ud83e\udd73\ud83e\udd73",
        "author_id": "273172592",
        "created_at": "2022-05-20T15:40:23.000Z",
        "public_metrics": {
            "retweet_count": 0,
            "reply_count": 0,
            "like_count": 2,
            "quote_count": 0
        },
        "edit_history_tweet_ids": [
            "1527675610788765696"
        ],
        "lang": "en"
    },
    {
        "geo": {
            "place_id": "fe4b2b8e51cc85c1",
            "coordinates": {
                "type": "Point",
                "coordinates": [
                    -84.57879707,
                    33.81894051
                ]
            }
        },
        "id": "1513323152889196545",
        "text": "This chocolate beauty my Big lil sis Aishia Thurman is my Shero today she saved me and she fed me she blessed my whole soul love you and thank you for taking care of your baby sis @ Mexico Lindo Restaurant Mableton https://t.co/jLqt4uSK9c",
        "author_id": "785730660",
        "created_at": "2022-04-11T01:08:50.000Z",
        "public_metrics": {
            "retweet_count": 0,
            "reply_count": 0,
            "like_count": 0,
            "quote_count": 0
        },
        "edit_history_tweet_ids": [
            "1513323152889196545"
        ],
        "lang": "en"
    },
    {
        "geo": {
            "place_id": "fe4b2b8e51cc85c1"
        },
        "id": "1512758829884350464",
        "text": "it\u2019s the restaurant for me \ud83d\ude0d https://t.co/iRGc2DhW93",
        "author_id": "183499699",
        "created_at": "2022-04-09T11:46:25.000Z",
        "public_metrics": {
            "retweet_count": 0,
            "reply_count": 0,
            "like_count": 1,
            "quote_count": 0
        },
        "edit_history_tweet_ids": [
            "1512758829884350464"
        ],
        "lang": "en"
    },
    {
        "geo": {
            "place_id": "fe4b2b8e51cc85c1",
            "coordinates": {
                "type": "Point",
                "coordinates": [
                    -84.51574708,
                    33.79953002
                ]
            }
        },
        "id": "1506143543286448129",
        "text": "Just posted a photo @ Cafe' Social House https://t.co/1iNiTpAjDS",
        "author_id": "24386170",
        "created_at": "2022-03-22T05:39:38.000Z",
        "public_metrics": {
            "retweet_count": 0,
            "reply_count": 0,
            "like_count": 0,
            "quote_count": 0
        },
        "edit_history_tweet_ids": [
            "1506143543286448129"
        ],
        "lang": "en"
    },
    {
        "geo": {
            "place_id": "fe4b2b8e51cc85c1",
            "coordinates": {
                "type": "Point",
                "coordinates": [
                    -84.5604237,
                    33.81290222
                ]
            }
        },
        "id": "1495053646815535107",
        "text": "Let's get it in with the @uptowncarclub for Cards and Cars. Today 1p-6p. \nACCESS LOUNGE 185 Veterans Memorial Hwy SE Mableton, GA 30126\nFor info contact 678-471-0250 @ Access Restaurant and Lounge https://t.co/fVB7cPvgor",
        "author_id": "41431196",
        "created_at": "2022-02-19T15:12:20.000Z",
        "public_metrics": {
            "retweet_count": 0,
            "reply_count": 0,
            "like_count": 0,
            "quote_count": 0
        },
        "edit_history_tweet_ids": [
            "1495053646815535107"
        ],
        "lang": "en"
    },
    {
        "geo": {
            "place_id": "fe4b2b8e51cc85c1"
        },
        "id": "1494081630142615557",
        "text": "so many fine women be coming into our restaurant \ud83e\udd26\ud83c\udfff\u200d\u2642\ufe0f",
        "author_id": "243749379",
        "created_at": "2022-02-16T22:49:53.000Z",
        "public_metrics": {
            "retweet_count": 0,
            "reply_count": 0,
            "like_count": 1,
            "quote_count": 0
        },
        "edit_history_tweet_ids": [
            "1494081630142615557"
        ],
        "lang": "en"
    },
    {
        "geo": {
            "place_id": "fe4b2b8e51cc85c1"
        },
        "id": "1490094939497279489",
        "text": "someone come pull up on me at da restaurant \ni\u2019m bored",
        "author_id": "243749379",
        "created_at": "2022-02-05T22:48:12.000Z",
        "public_metrics": {
            "retweet_count": 0,
            "reply_count": 0,
            "like_count": 0,
            "quote_count": 0
        },
        "edit_history_tweet_ids": [
            "1490094939497279489"
        ],
        "lang": "en"
    },
    {
        "geo": {
            "place_id": "fe4b2b8e51cc85c1",
            "coordinates": {
                "type": "Point",
                "coordinates": [
                    -84.5815105,
                    33.81774154
                ]
            }
        },
        "id": "1489795390991998982",
        "text": "Currently #campatl #westsidega @ Sky Restaurant Bar and Grill https://t.co/9LwXd57HL6",
        "author_id": "1636362595",
        "created_at": "2022-02-05T02:57:54.000Z",
        "public_metrics": {
            "retweet_count": 1,
            "reply_count": 0,
            "like_count": 0,
            "quote_count": 0
        },
        "edit_history_tweet_ids": [
            "1489795390991998982"
        ],
        "lang": "en"
    },
    {
        "geo": {
            "place_id": "fe4b2b8e51cc85c1"
        },
        "id": "1489048717416181761",
        "text": "Pero mi droga es las alitas del WING-STOP y el caf\u00e9 con pan. https://t.co/m5Jb31hPj5",
        "author_id": "29722841",
        "created_at": "2022-02-03T01:30:54.000Z",
        "public_metrics": {
            "retweet_count": 0,
            "reply_count": 0,
            "like_count": 0,
            "quote_count": 0
        },
        "edit_history_tweet_ids": [
            "1489048717416181761"
        ],
        "lang": "es"
    },
    {
        "geo": {
            "place_id": "fe4b2b8e51cc85c1",
            "coordinates": {
                "type": "Point",
                "coordinates": [
                    -84.51574708,
                    33.79953002
                ]
            }
        },
        "id": "1483256545362292737",
        "text": "Just posted a photo @ Cafe' Social House https://t.co/11ZnGgGc72",
        "author_id": "270637221",
        "created_at": "2022-01-18T01:54:52.000Z",
        "public_metrics": {
            "retweet_count": 0,
            "reply_count": 0,
            "like_count": 0,
            "quote_count": 0
        },
        "edit_history_tweet_ids": [
            "1483256545362292737"
        ],
        "lang": "en"
    },
    {
        "geo": {
            "place_id": "fe4b2b8e51cc85c1",
            "coordinates": {
                "type": "Point",
                "coordinates": [
                    -84.5604237,
                    33.81290222
                ]
            }
        },
        "id": "1478703429824532484",
        "text": "Just posted a photo @ Access Restaurant and Lounge https://t.co/1Wzn608yHG",
        "author_id": "203828921",
        "created_at": "2022-01-05T12:22:25.000Z",
        "public_metrics": {
            "retweet_count": 0,
            "reply_count": 0,
            "like_count": 0,
            "quote_count": 0
        },
        "edit_history_tweet_ids": [
            "1478703429824532484"
        ],
        "lang": "en"
    },
    {
        "geo": {
            "place_id": "fe4b2b8e51cc85c1"
        },
        "id": "1471163206391447563",
        "text": "Active footage of me getting dragged across the bar last Sunday at Roscoes \ud83d\ude29 https://t.co/jvsjenhcAp",
        "author_id": "229714180",
        "created_at": "2021-12-15T17:00:15.000Z",
        "public_metrics": {
            "retweet_count": 0,
            "reply_count": 0,
            "like_count": 1,
            "quote_count": 0
        },
        "edit_history_tweet_ids": [
            "1471163206391447563"
        ],
        "lang": "en"
    },
    {
        "geo": {
            "place_id": "fe4b2b8e51cc85c1",
            "coordinates": {
                "type": "Point",
                "coordinates": [
                    -84.5815105,
                    33.81774154
                ]
            }
        },
        "id": "1469884709131935747",
        "text": "Missing 4 but the team is now complete. 2022 is going to be a Problem!!!. #campatl @ Sky Restaurant Bar and Grill https://t.co/OptDY6YoAQ",
        "author_id": "1636362595",
        "created_at": "2021-12-12T04:19:58.000Z",
        "public_metrics": {
            "retweet_count": 0,
            "reply_count": 0,
            "like_count": 0,
            "quote_count": 0
        },
        "edit_history_tweet_ids": [
            "1469884709131935747"
        ],
        "lang": "en"
    },
    {
        "geo": {
            "place_id": "fe4b2b8e51cc85c1"
        },
        "id": "1466466349127974920",
        "text": "@dominos  please take back your free pizza 2 topping points you give me for last fuck up. Because I tried to try you out again and once again fail. I even ordered 10am online to be delivered for 12:30pm then I had to call the restaurant to cancel 12:56pm",
        "author_id": "2714535675",
        "created_at": "2021-12-02T17:56:37.000Z",
        "public_metrics": {
            "retweet_count": 0,
            "reply_count": 1,
            "like_count": 0,
            "quote_count": 0
        },
        "edit_history_tweet_ids": [
            "1466466349127974920"
        ],
        "lang": "en"
    },
    {
        "geo": {
            "place_id": "fe4b2b8e51cc85c1"
        },
        "id": "1452818029373427715",
        "text": "whoever robbed me at the green bar probably unintentionally used my money to buy me drinks later in the night so i can\u2019t even complain",
        "author_id": "3056633897",
        "created_at": "2021-10-26T02:03:04.000Z",
        "public_metrics": {
            "retweet_count": 0,
            "reply_count": 0,
            "like_count": 2,
            "quote_count": 0
        },
        "edit_history_tweet_ids": [
            "1452818029373427715"
        ],
        "lang": "en"
    },
    {
        "geo": {
            "place_id": "fe4b2b8e51cc85c1",
            "coordinates": {
                "type": "Point",
                "coordinates": [
                    -84.5604237,
                    33.81290222
                ]
            }
        },
        "id": "1451602140229681153",
        "text": "\ud83c\udf51\ud83d\udd25Yo ATLANTA WUDDUP!!! Comin to Mableton wit da funny TONIGHT at 9pm!!! See yall thurr #comedygrind #yeenyeen @ Access Restaurant and Lounge https://t.co/Pf29CWmjy5",
        "author_id": "307943359",
        "created_at": "2021-10-22T17:31:34.000Z",
        "public_metrics": {
            "retweet_count": 0,
            "reply_count": 0,
            "like_count": 0,
            "quote_count": 0
        },
        "edit_history_tweet_ids": [
            "1451602140229681153"
        ],
        "lang": "en"
    },
    {
        "geo": {
            "place_id": "fe4b2b8e51cc85c1"
        },
        "id": "1443338054551363590",
        "text": "Dating in 2021 be like\u2026 \n\nHer: Hey, you want to go to Ruth Chris this weekend? My treat, it\u2019s my favorite restaurant. \n\nMe: I would Jessica, but I\u2019m going to Zanzibar this weekend. But have some steak for me.",
        "author_id": "724391925428695041",
        "created_at": "2021-09-29T22:13:02.000Z",
        "public_metrics": {
            "retweet_count": 0,
            "reply_count": 1,
            "like_count": 3,
            "quote_count": 0
        },
        "edit_history_tweet_ids": [
            "1443338054551363590"
        ],
        "lang": "en"
    },
    {
        "geo": {
            "place_id": "fe4b2b8e51cc85c1",
            "coordinates": {
                "type": "Point",
                "coordinates": [
                    -84.568787,
                    33.816778
                ]
            }
        },
        "id": "1441443771896537092",
        "text": "Because Fridays are for male lingerie! \ud83d\ude02\ud83e\udd37\ud83c\udffd\u200d\u2642\ufe0f#azul #fbf #bars #art @ Rancho \"El Molcajete\" Mexican Restaurant https://t.co/YnDzHb1P3n",
        "author_id": "74044726",
        "created_at": "2021-09-24T16:45:50.000Z",
        "public_metrics": {
            "retweet_count": 0,
            "reply_count": 0,
            "like_count": 0,
            "quote_count": 0
        },
        "edit_history_tweet_ids": [
            "1441443771896537092"
        ],
        "lang": "en"
    },
    {
        "geo": {
            "place_id": "fe4b2b8e51cc85c1"
        },
        "id": "1434222459713118216",
        "text": "@inclasswithcarr @karenhunter @AfricanaCarr @knarrative_ Performing weekends while working on the Railroad. Not too many people knew my 2nd career. It was top secret until they begin reading NJ &amp; NY article's on the trains.  We had hours of service rules. Brooklyn Up Over Jazz Cafe. \ud83d\ude09 \n\nhttps://t.co/1QKDi9e7ZI",
        "author_id": "21142713",
        "created_at": "2021-09-04T18:30:55.000Z",
        "public_metrics": {
            "retweet_count": 0,
            "reply_count": 0,
            "like_count": 1,
            "quote_count": 0
        },
        "edit_history_tweet_ids": [
            "1434222459713118216"
        ],
        "lang": "en"
    },
    {
        "geo": {
            "place_id": "fe4b2b8e51cc85c1"
        },
        "id": "1432759323537690627",
        "text": "I WILL BE AT THE BAR, WITH MY HEAD ON THE BAR\n\ud83d\udcad THINKING OUT LOUD: FUCKING DRUNKARDS!!!! HAHAHAHAHAHAHAHAHAHAHA!!!! \n\nIN A SUPER ARROGANT DEEP INTERNAL VOICE...\n\nHAHAHAHAHAHA!!!!",
        "author_id": "27371321",
        "created_at": "2021-08-31T17:36:56.000Z",
        "public_metrics": {
            "retweet_count": 0,
            "reply_count": 0,
            "like_count": 0,
            "quote_count": 0
        },
        "edit_history_tweet_ids": [
            "1432759323537690627"
        ],
        "lang": "en"
    },
    {
        "geo": {
            "place_id": "fe4b2b8e51cc85c1"
        },
        "id": "1431688796723159049",
        "text": "is that chinese restaurant on mlk on the west side still open?",
        "author_id": "1064194967952871424",
        "created_at": "2021-08-28T18:43:03.000Z",
        "public_metrics": {
            "retweet_count": 0,
            "reply_count": 0,
            "like_count": 0,
            "quote_count": 0
        },
        "edit_history_tweet_ids": [
            "1431688796723159049"
        ],
        "lang": "en"
    },
    {
        "geo": {
            "place_id": "fe4b2b8e51cc85c1"
        },
        "id": "1431279994484006913",
        "text": "Damn I miss going to a #HBCU and going to the cafe for fired chicken Fridays",
        "author_id": "250368700",
        "created_at": "2021-08-27T15:38:37.000Z",
        "public_metrics": {
            "retweet_count": 0,
            "reply_count": 0,
            "like_count": 0,
            "quote_count": 0
        },
        "edit_history_tweet_ids": [
            "1431279994484006913"
        ],
        "lang": "en"
    },
    {
        "geo": {
            "place_id": "fe4b2b8e51cc85c1"
        },
        "id": "1429793482001035272",
        "text": "@calvinjburke @joeehpowell Cripes, it was even worse than I was expecting, and my bar was on the ground. We definitely could have done without the exgay story! \ud83d\ude29",
        "author_id": "46476940",
        "created_at": "2021-08-23T13:11:45.000Z",
        "public_metrics": {
            "retweet_count": 0,
            "reply_count": 0,
            "like_count": 0,
            "quote_count": 0
        },
        "edit_history_tweet_ids": [
            "1429793482001035272"
        ],
        "lang": "en"
    },
    {
        "geo": {
            "place_id": "37ba60eb7c207199",
            "coordinates": {
                "type": "Point",
                "coordinates": [
                    -84.53889239,
                    33.81981982
                ]
            }
        },
        "id": "1424895682784239622",
        "text": "Now how ironic is it that Maurice wouldn't even tell Kimmie about Monster's vaping but want her to sit up in the restaurant &amp; take the meeting with Monsters mom in his absence because he had another meeting to attend to. If I were Kimmie I would have left before he did. #LAMH",
        "author_id": "405014532",
        "created_at": "2021-08-10T00:49:38.000Z",
        "public_metrics": {
            "retweet_count": 1,
            "reply_count": 1,
            "like_count": 3,
            "quote_count": 0
        },
        "edit_history_tweet_ids": [
            "1424895682784239622"
        ],
        "lang": "en"
    },
    {
        "geo": {
            "place_id": "fe4b2b8e51cc85c1",
            "coordinates": {
                "type": "Point",
                "coordinates": [
                    -84.5815105,
                    33.81774154
                ]
            }
        },
        "id": "1424227129353461762",
        "text": "Pt2 #campatl @ Sky Restaurant Bar and Grill https://t.co/nh7Llwv3pU",
        "author_id": "1636362595",
        "created_at": "2021-08-08T04:33:03.000Z",
        "public_metrics": {
            "retweet_count": 0,
            "reply_count": 0,
            "like_count": 0,
            "quote_count": 0
        },
        "edit_history_tweet_ids": [
            "1424227129353461762"
        ],
        "lang": "en"
    },
    {
        "geo": {
            "place_id": "fe4b2b8e51cc85c1",
            "coordinates": {
                "type": "Point",
                "coordinates": [
                    -84.5815105,
                    33.81774154
                ]
            }
        },
        "id": "1424218622923354116",
        "text": "Currently @ Sky Restaurant Bar and Grill https://t.co/VwaJoOIDM1",
        "author_id": "1636362595",
        "created_at": "2021-08-08T03:59:15.000Z",
        "public_metrics": {
            "retweet_count": 0,
            "reply_count": 0,
            "like_count": 0,
            "quote_count": 0
        },
        "edit_history_tweet_ids": [
            "1424218622923354116"
        ],
        "lang": "en"
    },
    {
        "geo": {
            "place_id": "fe4b2b8e51cc85c1"
        },
        "id": "1424187175298600962",
        "text": "I had a drink at cypress hill restaurant one sip I was hot as a mf \ud83d\ude2d I said what y\u2019all put in this hell!? \ud83d\ude2d",
        "author_id": "1118665720643112960",
        "created_at": "2021-08-08T01:54:17.000Z",
        "public_metrics": {
            "retweet_count": 0,
            "reply_count": 0,
            "like_count": 0,
            "quote_count": 0
        },
        "edit_history_tweet_ids": [
            "1424187175298600962"
        ],
        "lang": "en"
    },
    {
        "geo": {
            "place_id": "fe4b2b8e51cc85c1"
        },
        "id": "1415452850537353226",
        "text": "get me\ud83d\ude02\ud83e\udd23 cs what\u2019s better than publix bakery? https://t.co/nCDGy8BPZ2",
        "author_id": "3292267246",
        "created_at": "2021-07-14T23:27:12.000Z",
        "public_metrics": {
            "retweet_count": 0,
            "reply_count": 0,
            "like_count": 0,
            "quote_count": 0
        },
        "edit_history_tweet_ids": [
            "1415452850537353226"
        ],
        "lang": "en"
    },
    {
        "geo": {
            "place_id": "0ea3445e0a150000"
        },
        "id": "1413522304521445383",
        "text": "Still up\u2026 at Cafe social before i go to my appointment. https://t.co/2cwHB11FJS",
        "author_id": "772139403540062210",
        "created_at": "2021-07-09T15:35:54.000Z",
        "public_metrics": {
            "retweet_count": 0,
            "reply_count": 0,
            "like_count": 3,
            "quote_count": 0
        },
        "edit_history_tweet_ids": [
            "1413522304521445383"
        ],
        "lang": "en"
    },
    {
        "geo": {
            "place_id": "fe4b2b8e51cc85c1"
        },
        "id": "1410788632475099136",
        "text": "I gotta stop buying 30 shots at the bar \ud83d\ude02\ud83d\ude02 I just took like 8 back to back",
        "author_id": "1118665720643112960",
        "created_at": "2021-07-02T02:33:15.000Z",
        "public_metrics": {
            "retweet_count": 0,
            "reply_count": 0,
            "like_count": 0,
            "quote_count": 0
        },
        "edit_history_tweet_ids": [
            "1410788632475099136"
        ],
        "lang": "en"
    },
    {
        "geo": {
            "place_id": "fe4b2b8e51cc85c1",
            "coordinates": {
                "type": "Point",
                "coordinates": [
                    -84.51574708,
                    33.79953002
                ]
            }
        },
        "id": "1408821586866577409",
        "text": "Thanks for the recommendation @Melissa!!!  #sefcaresaturday @ Cafe' Social House https://t.co/gNrakisAjL",
        "author_id": "960004443797368832",
        "created_at": "2021-06-26T16:16:55.000Z",
        "public_metrics": {
            "retweet_count": 0,
            "reply_count": 0,
            "like_count": 0,
            "quote_count": 0
        },
        "edit_history_tweet_ids": [
            "1408821586866577409"
        ],
        "lang": "en"
    },
    {
        "geo": {
            "place_id": "5b8df26e6d0be60b",
            "coordinates": {
                "type": "Point",
                "coordinates": [
                    -84.5131989,
                    33.7987366
                ]
            }
        },
        "id": "1402813682724257793",
        "text": "Drinking a Bud Light by @AnheuserBusch @ Pizza Bar \u2014 https://t.co/DPEwCol2Sx",
        "author_id": "116772645",
        "created_at": "2021-06-10T02:23:39.000Z",
        "public_metrics": {
            "retweet_count": 0,
            "reply_count": 0,
            "like_count": 0,
            "quote_count": 0
        },
        "edit_history_tweet_ids": [
            "1402813682724257793"
        ],
        "lang": "en"
    },
    {
        "geo": {
            "place_id": "0fc3412bb6155001"
        },
        "id": "1393641665039151108",
        "text": "if you\u2019re in atlanta check out our restaurant https://t.co/G76uTnvC8s \ud83c\uddef\ud83c\uddf2\ud83c\udf7d https://t.co/ffAkNMbbKG",
        "author_id": "243749379",
        "created_at": "2021-05-15T18:57:20.000Z",
        "public_metrics": {
            "retweet_count": 6,
            "reply_count": 0,
            "like_count": 10,
            "quote_count": 0
        },
        "edit_history_tweet_ids": [
            "1393641665039151108"
        ],
        "lang": "en"
    },
    {
        "geo": {
            "place_id": "fe4b2b8e51cc85c1",
            "coordinates": {
                "type": "Point",
                "coordinates": [
                    -84.5607154,
                    33.81262628
                ]
            }
        },
        "id": "1388671656944705540",
        "text": "Just posted a photo @ Tonita's Restaurant Bar and Grill https://t.co/GSz1P9WWaV",
        "author_id": "552414460",
        "created_at": "2021-05-02T01:48:17.000Z",
        "public_metrics": {
            "retweet_count": 0,
            "reply_count": 0,
            "like_count": 0,
            "quote_count": 0
        },
        "edit_history_tweet_ids": [
            "1388671656944705540"
        ],
        "lang": "en"
    },
    {
        "geo": {
            "place_id": "fe4b2b8e51cc85c1"
        },
        "id": "1388588886973108228",
        "text": "I\u2019m bouta get drunk at the bar",
        "author_id": "250368700",
        "created_at": "2021-05-01T20:19:24.000Z",
        "public_metrics": {
            "retweet_count": 0,
            "reply_count": 0,
            "like_count": 1,
            "quote_count": 0
        },
        "edit_history_tweet_ids": [
            "1388588886973108228"
        ],
        "lang": "en"
    },
    {
        "geo": {
            "place_id": "fe4b2b8e51cc85c1"
        },
        "id": "1378351110600134659",
        "text": "@ProvAtlantic @jmjafrx @BlackDigitalHum @ruha9 @safiyanoble They too, are Thee Standard..seminal work in Black DH. Forever grateful to @Sarah_Patterson and @jimccasey1 for setting the bar high and directing my path at my 1st @HILT_DH training. @CCP_org",
        "author_id": "2900469246",
        "created_at": "2021-04-03T14:18:07.000Z",
        "public_metrics": {
            "retweet_count": 2,
            "reply_count": 2,
            "like_count": 5,
            "quote_count": 0
        },
        "edit_history_tweet_ids": [
            "1378351110600134659"
        ],
        "lang": "en"
    },
    {
        "geo": {
            "place_id": "fe4b2b8e51cc85c1",
            "coordinates": {
                "type": "Point",
                "coordinates": [
                    -84.51574708,
                    33.79953002
                ]
            }
        },
        "id": "1373366193235496961",
        "text": "Cousins in ATL @ Cafe' Social House https://t.co/ZToy5yFy7j",
        "author_id": "32586013",
        "created_at": "2021-03-20T20:09:51.000Z",
        "public_metrics": {
            "retweet_count": 0,
            "reply_count": 0,
            "like_count": 0,
            "quote_count": 0
        },
        "edit_history_tweet_ids": [
            "1373366193235496961"
        ],
        "lang": "en"
    },
    {
        "geo": {
            "place_id": "fe4b2b8e51cc85c1",
            "coordinates": {
                "type": "Point",
                "coordinates": [
                    -84.5815105,
                    33.81774154
                ]
            }
        },
        "id": "1372239507848847360",
        "text": "Tonight!!! Right after work @ Sky Restaurant Bar and Grill https://t.co/MqvD2gcbz5",
        "author_id": "1636362595",
        "created_at": "2021-03-17T17:32:48.000Z",
        "public_metrics": {
            "retweet_count": 0,
            "reply_count": 0,
            "like_count": 0,
            "quote_count": 0
        },
        "edit_history_tweet_ids": [
            "1372239507848847360"
        ],
        "lang": "en"
    },
    {
        "geo": {
            "place_id": "fe4b2b8e51cc85c1",
            "coordinates": {
                "type": "Point",
                "coordinates": [
                    -84.5815105,
                    33.81774154
                ]
            }
        },
        "id": "1362903175821426693",
        "text": "I\u2019m Back !!! Tonight @ Sky Restaurant Bar and Grill https://t.co/xasQsFodqI",
        "author_id": "1636362595",
        "created_at": "2021-02-19T23:13:33.000Z",
        "public_metrics": {
            "retweet_count": 0,
            "reply_count": 0,
            "like_count": 0,
            "quote_count": 0
        },
        "edit_history_tweet_ids": [
            "1362903175821426693"
        ],
        "lang": "en"
    },
    {
        "geo": {
            "place_id": "fe4b2b8e51cc85c1"
        },
        "id": "1361852926168301580",
        "text": "Gumbeaux Cajun cafe sounds sooo good right now... but they closed",
        "author_id": "85354782",
        "created_at": "2021-02-17T01:40:14.000Z",
        "public_metrics": {
            "retweet_count": 0,
            "reply_count": 0,
            "like_count": 1,
            "quote_count": 0
        },
        "edit_history_tweet_ids": [
            "1361852926168301580"
        ],
        "lang": "en"
    },
    {
        "geo": {
            "place_id": "fe4b2b8e51cc85c1",
            "coordinates": {
                "type": "Point",
                "coordinates": [
                    -84.56058015,
                    33.81981982
                ]
            }
        },
        "id": "1359675189357928448",
        "text": "I saw a post where a dad in my hometown closed down a very pricey restaurant for the afternoon so he could take his three daughters on a Valentine's date. Not only is that Uber sweet, but safe &amp; those girls will NEVER forget it. That's a true #GirlDad. Love it! \u2764\ufe0f",
        "author_id": "405014532",
        "created_at": "2021-02-11T01:26:41.000Z",
        "public_metrics": {
            "retweet_count": 0,
            "reply_count": 0,
            "like_count": 0,
            "quote_count": 0
        },
        "edit_history_tweet_ids": [
            "1359675189357928448"
        ],
        "lang": "en"
    },
    {
        "geo": {
            "place_id": "fe4b2b8e51cc85c1"
        },
        "id": "1350510405882433539",
        "text": "Murkowski: Bar Trump From Ever Holding Any Office Again https://t.co/jolg25dbYV",
        "author_id": "1266404819243327488",
        "created_at": "2021-01-16T18:29:06.000Z",
        "public_metrics": {
            "retweet_count": 0,
            "reply_count": 0,
            "like_count": 0,
            "quote_count": 0
        },
        "edit_history_tweet_ids": [
            "1350510405882433539"
        ],
        "lang": "en"
    },
    {
        "geo": {
            "place_id": "fe4b2b8e51cc85c1",
            "coordinates": {
                "type": "Point",
                "coordinates": [
                    -84.5815105,
                    33.81774154
                ]
            }
        },
        "id": "1344845997478993920",
        "text": "The warm up @ Sky Restaurant Bar and Grill https://t.co/BaG9H0txQ0",
        "author_id": "1636362595",
        "created_at": "2021-01-01T03:20:46.000Z",
        "public_metrics": {
            "retweet_count": 0,
            "reply_count": 0,
            "like_count": 0,
            "quote_count": 0
        },
        "edit_history_tweet_ids": [
            "1344845997478993920"
        ],
        "lang": "en"
    },
    {
        "geo": {
            "place_id": "fe4b2b8e51cc85c1",
            "coordinates": {
                "type": "Point",
                "coordinates": [
                    -84.51574708,
                    33.79953002
                ]
            }
        },
        "id": "1343244177757319168",
        "text": "Breakfast was great this morning with my fam before they leave. @ Cafe' Social House https://t.co/7t7DccBn5B",
        "author_id": "47193640",
        "created_at": "2020-12-27T17:15:42.000Z",
        "public_metrics": {
            "retweet_count": 0,
            "reply_count": 0,
            "like_count": 0,
            "quote_count": 0
        },
        "edit_history_tweet_ids": [
            "1343244177757319168"
        ],
        "lang": "en"
    },
    {
        "geo": {
            "place_id": "fe4b2b8e51cc85c1",
            "coordinates": {
                "type": "Point",
                "coordinates": [
                    -84.5815105,
                    33.81774154
                ]
            }
        },
        "id": "1342953192057921537",
        "text": "\ud83d\udd09Tonight \ud83d\udd0a #sayless #campatl #djrichsample #927music #westsideatlanta @ Sky Restaurant Bar and Grill https://t.co/sQwHlgg8Vz",
        "author_id": "1636362595",
        "created_at": "2020-12-26T21:59:26.000Z",
        "public_metrics": {
            "retweet_count": 0,
            "reply_count": 0,
            "like_count": 0,
            "quote_count": 0
        },
        "edit_history_tweet_ids": [
            "1342953192057921537"
        ],
        "lang": "en"
    },
    {
        "geo": {
            "place_id": "fe4b2b8e51cc85c1",
            "coordinates": {
                "type": "Point",
                "coordinates": [
                    -84.5815105,
                    33.81774154
                ]
            }
        },
        "id": "1337486469859069954",
        "text": "Tonight 9pm @ Sky Restaurant Bar and Grill https://t.co/Lm0BpjCpb6",
        "author_id": "1636362595",
        "created_at": "2020-12-11T19:56:38.000Z",
        "public_metrics": {
            "retweet_count": 0,
            "reply_count": 0,
            "like_count": 0,
            "quote_count": 0
        },
        "edit_history_tweet_ids": [
            "1337486469859069954"
        ],
        "lang": "en"
    },
    {
        "geo": {
            "place_id": "fe4b2b8e51cc85c1"
        },
        "id": "1335642616478756865",
        "text": "Sooo would yal still go in a Chinese restaurant if you see cats near the entrance eating AND drinking from pet bowls ??!!! Likeeeeeeeee WTF pets? Dinner? Idk",
        "author_id": "450844309",
        "created_at": "2020-12-06T17:49:49.000Z",
        "public_metrics": {
            "retweet_count": 0,
            "reply_count": 0,
            "like_count": 0,
            "quote_count": 0
        },
        "edit_history_tweet_ids": [
            "1335642616478756865"
        ],
        "lang": "en"
    },
    {
        "geo": {
            "place_id": "fe4b2b8e51cc85c1"
        },
        "id": "1333963386883764224",
        "text": "@GambxnoHuncho \ud83e\uddd0ok den lol I was like das a bar \ud83d\ude02",
        "author_id": "2871246915",
        "created_at": "2020-12-02T02:37:09.000Z",
        "public_metrics": {
            "retweet_count": 0,
            "reply_count": 0,
            "like_count": 1,
            "quote_count": 0
        },
        "edit_history_tweet_ids": [
            "1333963386883764224"
        ],
        "lang": "en"
    },
    {
        "geo": {
            "place_id": "fe4b2b8e51cc85c1"
        },
        "id": "1333381412855181312",
        "text": "Get out that man's restaurant showing y'all natural black asses!",
        "author_id": "133097630",
        "created_at": "2020-11-30T12:04:36.000Z",
        "public_metrics": {
            "retweet_count": 0,
            "reply_count": 0,
            "like_count": 0,
            "quote_count": 0
        },
        "edit_history_tweet_ids": [
            "1333381412855181312"
        ],
        "lang": "en"
    },
    {
        "geo": {
            "place_id": "0fc3412bb6155001"
        },
        "id": "1332775548712521730",
        "text": "if you\u2019re in atlanta, please make sure to stop by my family restaurant \ud83c\uddef\ud83c\uddf2\ud83c\udf7d serving authentic jamaican food! #SupportBlackOwnedBusinesses https://t.co/oYnOQluuDm",
        "author_id": "243749379",
        "created_at": "2020-11-28T19:57:07.000Z",
        "public_metrics": {
            "retweet_count": 48,
            "reply_count": 2,
            "like_count": 67,
            "quote_count": 3
        },
        "edit_history_tweet_ids": [
            "1332775548712521730"
        ],
        "lang": "en"
    },
    {
        "geo": {
            "place_id": "fe4b2b8e51cc85c1",
            "coordinates": {
                "type": "Point",
                "coordinates": [
                    -84.5815105,
                    33.81774154
                ]
            }
        },
        "id": "1332394636766273542",
        "text": "Tonight!!! 8pm S/O to all the outta owners coming thru #westsidega #campatl #Fairburnrd @ Sky Restaurant Bar and Grill https://t.co/fos7IS5soS",
        "author_id": "1636362595",
        "created_at": "2020-11-27T18:43:30.000Z",
        "public_metrics": {
            "retweet_count": 0,
            "reply_count": 0,
            "like_count": 0,
            "quote_count": 0
        },
        "edit_history_tweet_ids": [
            "1332394636766273542"
        ],
        "lang": "en"
    },
    {
        "geo": {
            "place_id": "fe4b2b8e51cc85c1",
            "coordinates": {
                "type": "Point",
                "coordinates": [
                    -84.5815105,
                    33.81774154
                ]
            }
        },
        "id": "1331428332211228675",
        "text": "A SKY shot @ Sky Restaurant Bar and Grill https://t.co/QgcitTi90u",
        "author_id": "1636362595",
        "created_at": "2020-11-25T02:43:45.000Z",
        "public_metrics": {
            "retweet_count": 0,
            "reply_count": 0,
            "like_count": 0,
            "quote_count": 0
        },
        "edit_history_tweet_ids": [
            "1331428332211228675"
        ],
        "lang": "en"
    },
    {
        "geo": {
            "place_id": "fe4b2b8e51cc85c1"
        },
        "id": "1330409374070747137",
        "text": "Role play kinda setup... I just met you downstairs at the bar I\u2019m not even from here \ud83e\udd23 https://t.co/Lsn1ocG1L9",
        "author_id": "153151374",
        "created_at": "2020-11-22T07:14:47.000Z",
        "public_metrics": {
            "retweet_count": 10,
            "reply_count": 4,
            "like_count": 69,
            "quote_count": 1
        },
        "edit_history_tweet_ids": [
            "1330409374070747137"
        ],
        "lang": "en"
    },
    {
        "geo": {
            "place_id": "fe4b2b8e51cc85c1",
            "coordinates": {
                "type": "Point",
                "coordinates": [
                    -84.5815105,
                    33.81774154
                ]
            }
        },
        "id": "1327817434468794368",
        "text": "Stop #2\n#queensnyc #campatl #westsideatlanta @ Sky Restaurant Bar and Grill https://t.co/ewrPJd8p7r",
        "author_id": "1636362595",
        "created_at": "2020-11-15T03:35:20.000Z",
        "public_metrics": {
            "retweet_count": 0,
            "reply_count": 0,
            "like_count": 0,
            "quote_count": 0
        },
        "edit_history_tweet_ids": [
            "1327817434468794368"
        ],
        "lang": "en"
    },
    {
        "geo": {
            "place_id": "fe4b2b8e51cc85c1",
            "coordinates": {
                "type": "Point",
                "coordinates": [
                    -84.5815105,
                    33.81774154
                ]
            }
        },
        "id": "1325300732862623753",
        "text": "Currently #campatl @ Sky Restaurant Bar and Grill https://t.co/fhmSklbx8G",
        "author_id": "1636362595",
        "created_at": "2020-11-08T04:54:52.000Z",
        "public_metrics": {
            "retweet_count": 0,
            "reply_count": 0,
            "like_count": 0,
            "quote_count": 0
        },
        "edit_history_tweet_ids": [
            "1325300732862623753"
        ],
        "lang": "en"
    },
    {
        "geo": {
            "place_id": "fe4b2b8e51cc85c1",
            "coordinates": {
                "type": "Point",
                "coordinates": [
                    -84.5815105,
                    33.81774154
                ]
            }
        },
        "id": "1324836036434751489",
        "text": "9pm Tonight @ Sky Restaurant Bar and Grill https://t.co/6yX35QgLAm",
        "author_id": "1636362595",
        "created_at": "2020-11-06T22:08:20.000Z",
        "public_metrics": {
            "retweet_count": 0,
            "reply_count": 0,
            "like_count": 0,
            "quote_count": 0
        },
        "edit_history_tweet_ids": [
            "1324836036434751489"
        ],
        "lang": "en"
    },
    {
        "geo": {
            "place_id": "fe4b2b8e51cc85c1",
            "coordinates": {
                "type": "Point",
                "coordinates": [
                    -84.5815105,
                    33.81774154
                ]
            }
        },
        "id": "1324795226247102464",
        "text": "Tonight 9pm!!! @sky.bar.mableton @ Sky Restaurant Bar and Grill https://t.co/gj9oBA5crn",
        "author_id": "1636362595",
        "created_at": "2020-11-06T19:26:10.000Z",
        "public_metrics": {
            "retweet_count": 0,
            "reply_count": 0,
            "like_count": 0,
            "quote_count": 0
        },
        "edit_history_tweet_ids": [
            "1324795226247102464"
        ],
        "lang": "en"
    },
    {
        "geo": {
            "place_id": "fe4b2b8e51cc85c1"
        },
        "id": "1323686096602079242",
        "text": "@Jayimarie Park Bar",
        "author_id": "1007886840",
        "created_at": "2020-11-03T17:58:52.000Z",
        "public_metrics": {
            "retweet_count": 0,
            "reply_count": 0,
            "like_count": 0,
            "quote_count": 0
        },
        "edit_history_tweet_ids": [
            "1323686096602079242"
        ],
        "lang": "en"
    },
    {
        "geo": {
            "place_id": "fe4b2b8e51cc85c1"
        },
        "id": "1318549274167250944",
        "text": "So proud of .@MabletonES STEAM Super Sleuths! The bar was set high &amp; these students &amp; their teacher took on the challenge! Check out my PBL STEAM Challenge .@nearpod I created https://t.co/9imJqi4pIi or use code TAQJB on Nearpod website #UtlimateLearningExperience https://t.co/UoVBPYC5Mc",
        "author_id": "3719165777",
        "created_at": "2020-10-20T13:46:59.000Z",
        "public_metrics": {
            "retweet_count": 2,
            "reply_count": 0,
            "like_count": 8,
            "quote_count": 0
        },
        "edit_history_tweet_ids": [
            "1318549274167250944"
        ],
        "lang": "en"
    },
    {
        "geo": {
            "place_id": "fe4b2b8e51cc85c1"
        },
        "id": "1317559479353958403",
        "text": "When I tell you the food at Yeah Man Jamaican Restaurant HITS!!! Baybayyyyy \ud83e\udd24\ud83d\ude0d I killed the oxtail and the curry chicken my two visits. And bossman at the counter is cool \u2014 great vibes \ud83c\uddef\ud83c\uddf2 BRANG YO ASS https://t.co/cZ4ApXCsFj",
        "author_id": "1405688622",
        "created_at": "2020-10-17T20:13:53.000Z",
        "public_metrics": {
            "retweet_count": 0,
            "reply_count": 0,
            "like_count": 1,
            "quote_count": 0
        },
        "edit_history_tweet_ids": [
            "1317559479353958403"
        ],
        "lang": "en"
    },
    {
        "geo": {
            "place_id": "fe4b2b8e51cc85c1"
        },
        "id": "1314006469642268672",
        "text": "I was doing so good at no alcohol October &amp; now I\u2019m somehow at the bar \ud83e\udd74",
        "author_id": "68486752",
        "created_at": "2020-10-08T00:55:30.000Z",
        "public_metrics": {
            "retweet_count": 0,
            "reply_count": 0,
            "like_count": 0,
            "quote_count": 0
        },
        "edit_history_tweet_ids": [
            "1314006469642268672"
        ],
        "lang": "en"
    },
    {
        "lang": "en",
        "public_metrics": {
            "retweet_count": 0,
            "reply_count": 0,
            "like_count": 0,
            "quote_count": 0
        },
        "author_id": "257737924",
        "id": "1309400491655397377",
        "created_at": "2020-09-25T07:52:59.000Z",
        "edit_history_tweet_ids": [
            "1309400491655397377"
        ],
        "text": "It\u2019s a Brazilian restaurant",
        "geo": {
            "place_id": "fe4b2b8e51cc85c1"
        }
    },
    {
        "lang": "en",
        "public_metrics": {
            "retweet_count": 0,
            "reply_count": 1,
            "like_count": 0,
            "quote_count": 0
        },
        "author_id": "257737924",
        "id": "1309400490254499840",
        "created_at": "2020-09-25T07:52:59.000Z",
        "edit_history_tweet_ids": [
            "1309400490254499840"
        ],
        "text": "One of our customers today complained about it not being enough of OUR people working at this restaurant.........",
        "geo": {
            "place_id": "fe4b2b8e51cc85c1"
        }
    },
    {
        "lang": "en",
        "public_metrics": {
            "retweet_count": 0,
            "reply_count": 0,
            "like_count": 0,
            "quote_count": 0
        },
        "author_id": "49196325",
        "id": "1308773468339605506",
        "created_at": "2020-09-23T14:21:25.000Z",
        "edit_history_tweet_ids": [
            "1308773468339605506"
        ],
        "text": "Where\u2019s a cute hookah bar?",
        "geo": {
            "place_id": "07d9d527e8c80002"
        }
    },
    {
        "lang": "en",
        "public_metrics": {
            "retweet_count": 0,
            "reply_count": 0,
            "like_count": 0,
            "quote_count": 0
        },
        "author_id": "47193640",
        "geo": {
            "coordinates": {
                "type": "Point",
                "coordinates": [
                    -84.51574708,
                    33.79953002
                ]
            },
            "place_id": "fe4b2b8e51cc85c1"
        },
        "id": "1307829059313897474",
        "created_at": "2020-09-20T23:48:40.000Z",
        "edit_history_tweet_ids": [
            "1307829059313897474"
        ],
        "text": "Margarita salmon, shrimp, and grits!\ud83d\ude0b\ud83d\ude0b @ Cafe' Social House https://t.co/lsBrAk6h0w"
    },
    {
        "lang": "en",
        "public_metrics": {
            "retweet_count": 0,
            "reply_count": 0,
            "like_count": 1,
            "quote_count": 0
        },
        "author_id": "2314831320",
        "id": "1306718147450470401",
        "created_at": "2020-09-17T22:14:18.000Z",
        "edit_history_tweet_ids": [
            "1306718147450470401"
        ],
        "text": "@jbwing_5 I like them too \ud83e\udd23 but the bar was set very low",
        "geo": {
            "place_id": "fe4b2b8e51cc85c1"
        }
    },
    {
        "lang": "en",
        "public_metrics": {
            "retweet_count": 0,
            "reply_count": 1,
            "like_count": 2,
            "quote_count": 0
        },
        "author_id": "18236610",
        "id": "1304466742463340551",
        "created_at": "2020-09-11T17:08:01.000Z",
        "edit_history_tweet_ids": [
            "1304466742463340551"
        ],
        "text": "Think it\u2019s gonna be a lobster roll for restaurant Friday",
        "geo": {
            "place_id": "fe4b2b8e51cc85c1"
        }
    },
    {
        "lang": "en",
        "public_metrics": {
            "retweet_count": 0,
            "reply_count": 0,
            "like_count": 0,
            "quote_count": 0
        },
        "author_id": "1636362595",
        "geo": {
            "coordinates": {
                "type": "Point",
                "coordinates": [
                    -84.5815105,
                    33.81774154
                ]
            },
            "place_id": "fe4b2b8e51cc85c1"
        },
        "id": "1302136959314337797",
        "created_at": "2020-09-05T06:50:18.000Z",
        "edit_history_tweet_ids": [
            "1302136959314337797"
        ],
        "text": "\ud83d\udea8 New Drip alert \ud83d\udea8 #prettytallempire @ Sky Restaurant Bar and Grill https://t.co/pp6obldXg8"
    },
    {
        "lang": "en",
        "public_metrics": {
            "retweet_count": 0,
            "reply_count": 0,
            "like_count": 3,
            "quote_count": 0
        },
        "author_id": "694638332366700546",
        "id": "1302101927547854850",
        "created_at": "2020-09-05T04:31:06.000Z",
        "edit_history_tweet_ids": [
            "1302101927547854850"
        ],
        "text": "It\u2019s pride and my cousins are taking me to some straight bar \ud83d\ude29\ud83d\ude29\ud83d\ude29 https://t.co/N7zuf2RHMG",
        "geo": {
            "place_id": "fe4b2b8e51cc85c1"
        }
    },
    {
        "lang": "en",
        "public_metrics": {
            "retweet_count": 0,
            "reply_count": 0,
            "like_count": 0,
            "quote_count": 0
        },
        "author_id": "15892715",
        "id": "1301693706546958337",
        "created_at": "2020-09-04T01:28:58.000Z",
        "edit_history_tweet_ids": [
            "1301693706546958337"
        ],
        "text": "@taffyakner I\u2019ve never seen it in real life, but a bartender at a restaurant I worked at in college asked me if I \u201cliked to party\u201d while tapping the side of his nose. \n\nI had never even been drunk before. So, that was a no from me.\n\nA few years later he was arrested in a giant cocaine bust.",
        "geo": {
            "place_id": "fe4b2b8e51cc85c1"
        }
    },
    {
        "lang": "en",
        "public_metrics": {
            "retweet_count": 0,
            "reply_count": 1,
            "like_count": 0,
            "quote_count": 0
        },
        "author_id": "243749379",
        "id": "1300868720332550151",
        "created_at": "2020-09-01T18:50:46.000Z",
        "edit_history_tweet_ids": [
            "1300868720332550151"
        ],
        "text": "@italgirl_ i\u2019ll make dat for u at home lol. don\u2019t need our restaurant for dat.",
        "geo": {
            "place_id": "fe4b2b8e51cc85c1"
        }
    },
    {
        "lang": "en",
        "public_metrics": {
            "retweet_count": 0,
            "reply_count": 1,
            "like_count": 0,
            "quote_count": 0
        },
        "author_id": "94866927",
        "id": "1300085526175854592",
        "created_at": "2020-08-30T14:58:38.000Z",
        "edit_history_tweet_ids": [
            "1300085526175854592"
        ],
        "text": "Another Broken Egg Cafe dont sound bad for breakfast",
        "geo": {
            "place_id": "fe4b2b8e51cc85c1"
        }
    },
    {
        "lang": "en",
        "public_metrics": {
            "retweet_count": 0,
            "reply_count": 0,
            "like_count": 0,
            "quote_count": 0
        },
        "author_id": "1636362595",
        "geo": {
            "coordinates": {
                "type": "Point",
                "coordinates": [
                    -84.5815105,
                    33.81774154
                ]
            },
            "place_id": "fe4b2b8e51cc85c1"
        },
        "id": "1299531630332108800",
        "created_at": "2020-08-29T02:17:39.000Z",
        "edit_history_tweet_ids": [
            "1299531630332108800"
        ],
        "text": "The support is real.                      https://t.co/kewkTKwCmE @ Sky Restaurant Bar and Grill https://t.co/WZHH5CLXix"
    },
    {
        "lang": "en",
        "public_metrics": {
            "retweet_count": 0,
            "reply_count": 0,
            "like_count": 0,
            "quote_count": 0
        },
        "author_id": "42698718",
        "geo": {
            "coordinates": {
                "type": "Point",
                "coordinates": [
                    -84.51574708,
                    33.79953002
                ]
            },
            "place_id": "fe4b2b8e51cc85c1"
        },
        "id": "1292526918655520774",
        "created_at": "2020-08-09T18:23:26.000Z",
        "edit_history_tweet_ids": [
            "1292526918655520774"
        ],
        "text": "\ud83e\udd70 She remembered who she was &amp; the game changed. \ud83d\ude18 @ Cafe' Social House https://t.co/OwCghOUoTo"
    },
    {
        "lang": "en",
        "public_metrics": {
            "retweet_count": 0,
            "reply_count": 0,
            "like_count": 0,
            "quote_count": 0
        },
        "author_id": "611665189",
        "geo": {
            "coordinates": {
                "type": "Point",
                "coordinates": [
                    -84.562134,
                    33.815494
                ]
            },
            "place_id": "fe4b2b8e51cc85c1"
        },
        "id": "1291879354859950081",
        "created_at": "2020-08-07T23:30:14.000Z",
        "edit_history_tweet_ids": [
            "1291879354859950081"
        ],
        "text": "Let\u2019s see! (@ Yeah Man Jamaican Restaurant in Mableton, GA) https://t.co/cP9WNRPoyL"
    },
    {
        "lang": "en",
        "public_metrics": {
            "retweet_count": 0,
            "reply_count": 1,
            "like_count": 1,
            "quote_count": 1
        },
        "author_id": "1335272293",
        "id": "1289239738709184512",
        "created_at": "2020-07-31T16:41:21.000Z",
        "edit_history_tweet_ids": [
            "1289239738709184512"
        ],
        "text": "I need a snicker bar.",
        "geo": {
            "place_id": "fe4b2b8e51cc85c1"
        }
    },
    {
        "lang": "en",
        "public_metrics": {
            "retweet_count": 0,
            "reply_count": 1,
            "like_count": 1,
            "quote_count": 0
        },
        "author_id": "369021041",
        "id": "1289074195494830080",
        "created_at": "2020-07-31T05:43:32.000Z",
        "edit_history_tweet_ids": [
            "1289074195494830080"
        ],
        "text": "@kaiynde friend can you make me a product to use in the suite on back bar? \ud83d\ude2d",
        "geo": {
            "place_id": "fe4b2b8e51cc85c1"
        }
    },
    {
        "lang": "en",
        "public_metrics": {
            "retweet_count": 0,
            "reply_count": 0,
            "like_count": 1,
            "quote_count": 0
        },
        "author_id": "16435316",
        "id": "1288558506732290050",
        "created_at": "2020-07-29T19:34:22.000Z",
        "edit_history_tweet_ids": [
            "1288558506732290050"
        ],
        "text": "@ClaireBerlinski I can\u2019t even imagine eating in a restaurant now.... I know it\u2019s a small thing in the scheme of things but it\u2019s hard to contemplate life post-virus. Being literally stuck in the US is something I never considered. What\u2019s happened here is appalling.",
        "geo": {
            "place_id": "fe4b2b8e51cc85c1"
        }
    },
    {
        "lang": "en",
        "public_metrics": {
            "retweet_count": 0,
            "reply_count": 0,
            "like_count": 0,
            "quote_count": 0
        },
        "author_id": "1368687482",
        "id": "1282497320052035584",
        "created_at": "2020-07-13T02:09:23.000Z",
        "edit_history_tweet_ids": [
            "1282497320052035584"
        ],
        "text": "so let me buy you a drink and we'll pretend that you think that I'm the man of your dreams come to life in a dive bar and we'll go over and over and over",
        "geo": {
            "place_id": "fe4b2b8e51cc85c1"
        }
    },
    {
        "lang": "en",
        "public_metrics": {
            "retweet_count": 0,
            "reply_count": 0,
            "like_count": 0,
            "quote_count": 0
        },
        "author_id": "551465966",
        "id": "1278066970383040513",
        "created_at": "2020-06-30T20:44:45.000Z",
        "edit_history_tweet_ids": [
            "1278066970383040513"
        ],
        "text": "Chicken, waffles, mac &amp; cheese, and candied yams courtesy of The Busy Bee Cafe, Atlanta, GA. YES LAWD!\n\ud83e\udd24\ud83d\ude0b https://t.co/MlFS5fiLSB",
        "geo": {
            "place_id": "fe4b2b8e51cc85c1"
        }
    },
    {
        "lang": "en",
        "public_metrics": {
            "retweet_count": 0,
            "reply_count": 0,
            "like_count": 1,
            "quote_count": 0
        },
        "author_id": "551465966",
        "id": "1277753950259875841",
        "created_at": "2020-06-30T00:00:55.000Z",
        "edit_history_tweet_ids": [
            "1277753950259875841"
        ],
        "text": "Me:\n1/4 St. Louis Arch\n1/4 part Slide-in\n1/4 Contortionist \n1/4 Kiss the Bar https://t.co/XXKk3Eq1vP",
        "geo": {
            "place_id": "fe4b2b8e51cc85c1"
        }
    },
    {
        "lang": "en",
        "public_metrics": {
            "retweet_count": 0,
            "reply_count": 0,
            "like_count": 2,
            "quote_count": 0
        },
        "author_id": "551465966",
        "id": "1276698727827361793",
        "created_at": "2020-06-27T02:07:51.000Z",
        "edit_history_tweet_ids": [
            "1276698727827361793"
        ],
        "text": "4. Alabama's official state restaurant HAS to be The Cracker Barrell.  It's like friggin' Starbucks and McDonald's in that state!  It's EVERYWHERE, BRO!",
        "geo": {
            "place_id": "fe4b2b8e51cc85c1"
        }
    },
    {
        "lang": "en",
        "public_metrics": {
            "retweet_count": 1,
            "reply_count": 2,
            "like_count": 2,
            "quote_count": 0
        },
        "author_id": "250368700",
        "id": "1274155150278565888",
        "created_at": "2020-06-20T01:40:35.000Z",
        "edit_history_tweet_ids": [
            "1274155150278565888"
        ],
        "text": "I just wanna sit at a bar &amp; DRANKKKKKKKKKK until I fall off the damn stool\ud83d\ude2d\ud83c\udf78\ud83c\udf7e",
        "geo": {
            "place_id": "fe4b2b8e51cc85c1"
        }
    },
    {
        "lang": "en",
        "public_metrics": {
            "retweet_count": 0,
            "reply_count": 0,
            "like_count": 0,
            "quote_count": 0
        },
        "author_id": "1636362595",
        "geo": {
            "coordinates": {
                "type": "Point",
                "coordinates": [
                    -84.5815105,
                    33.81774154
                ]
            },
            "place_id": "fe4b2b8e51cc85c1"
        },
        "id": "1271497471097630722",
        "created_at": "2020-06-12T17:39:55.000Z",
        "edit_history_tweet_ids": [
            "1271497471097630722"
        ],
        "text": "As we start to get back to neutral this is where I\u2019ll be tonight!!! #westsideatlanta #austell #lithiasprings #douglasvillega @ Sky Restaurant Bar and Grill https://t.co/GlcCDPuNDA"
    },
    {
        "lang": "en",
        "public_metrics": {
            "retweet_count": 0,
            "reply_count": 0,
            "like_count": 1,
            "quote_count": 0
        },
        "author_id": "613923729",
        "geo": {
            "coordinates": {
                "type": "Point",
                "coordinates": [
                    -84.58088636,
                    33.81782344
                ]
            },
            "place_id": "fe4b2b8e51cc85c1"
        },
        "id": "1267086904304054273",
        "created_at": "2020-05-31T13:33:53.000Z",
        "edit_history_tweet_ids": [
            "1267086904304054273"
        ],
        "text": "Updated #wellnessshots description...  #antiinflammatory #cobbcountyga #antioxidants #anticancerous #antiviral balances #cholesterol #bloodsugarbalance \n#fultoncountyga @ Paradise Smoothie Juice Bar https://t.co/bYK4dRvA3F"
    },
    {
        "lang": "en",
        "public_metrics": {
            "retweet_count": 0,
            "reply_count": 0,
            "like_count": 1,
            "quote_count": 0
        },
        "author_id": "613923729",
        "geo": {
            "coordinates": {
                "type": "Point",
                "coordinates": [
                    -84.58088636,
                    33.81782344
                ]
            },
            "place_id": "fe4b2b8e51cc85c1"
        },
        "id": "1266821063989768199",
        "created_at": "2020-05-30T19:57:32.000Z",
        "edit_history_tweet_ids": [
            "1266821063989768199"
        ],
        "text": "#mabletonga #mariettaga #austellga #douglasvillega #smyrnaga #viningsga #boostimmunesystem #veteranowned #healthiswealth #wellnessshots #atlanta #atl @ Paradise Smoothie Juice Bar https://t.co/89V4cDNfY9"
    },
    {
        "lang": "en",
        "public_metrics": {
            "retweet_count": 0,
            "reply_count": 0,
            "like_count": 1,
            "quote_count": 0
        },
        "author_id": "613923729",
        "geo": {
            "coordinates": {
                "type": "Point",
                "coordinates": [
                    -84.58088636,
                    33.81782344
                ]
            },
            "place_id": "fe4b2b8e51cc85c1"
        },
        "id": "1266789238865043456",
        "created_at": "2020-05-30T17:51:05.000Z",
        "edit_history_tweet_ids": [
            "1266789238865043456"
        ],
        "text": "#mabletonga #mariettaga #austellga #douglasvillega #smyrnaga #viningsga #atl #fultoncountyga #powderspringsga #healthiswealth #personaltrainer #atlanta @ Paradise Smoothie Juice Bar https://t.co/aKbaQUDeJJ"
    },
    {
        "lang": "en",
        "public_metrics": {
            "retweet_count": 0,
            "reply_count": 0,
            "like_count": 1,
            "quote_count": 0
        },
        "author_id": "613923729",
        "geo": {
            "coordinates": {
                "type": "Point",
                "coordinates": [
                    -84.58088636,
                    33.81782344
                ]
            },
            "place_id": "fe4b2b8e51cc85c1"
        },
        "id": "1266464067725791234",
        "created_at": "2020-05-29T20:18:58.000Z",
        "edit_history_tweet_ids": [
            "1266464067725791234"
        ],
        "text": "#mabletonga #mealreplacement #mariettaga #my2cents #Drink2Shrink @ Paradise Smoothie Juice Bar https://t.co/B6bepRPbkb"
    },
    {
        "lang": "en",
        "public_metrics": {
            "retweet_count": 0,
            "reply_count": 0,
            "like_count": 1,
            "quote_count": 0
        },
        "author_id": "613923729",
        "geo": {
            "coordinates": {
                "type": "Point",
                "coordinates": [
                    -84.58088636,
                    33.81782344
                ]
            },
            "place_id": "fe4b2b8e51cc85c1"
        },
        "id": "1266457234235691008",
        "created_at": "2020-05-29T19:51:48.000Z",
        "edit_history_tweet_ids": [
            "1266457234235691008"
        ],
        "text": "#Drink2Shrink #mabletonga #AllNatural #atl #fultoncountyga #powderspringsga #healthiswealth #austellga #smyrnaga #viningsga #veteranowned #healthiswealth @ Paradise Smoothie Juice Bar https://t.co/DAHaIqY9SV"
    },
    {
        "lang": "en",
        "public_metrics": {
            "retweet_count": 0,
            "reply_count": 0,
            "like_count": 1,
            "quote_count": 0
        },
        "author_id": "47622850",
        "id": "1263882350016057347",
        "created_at": "2020-05-22T17:20:08.000Z",
        "edit_history_tweet_ids": [
            "1263882350016057347"
        ],
        "text": "2 pompous F'NG idiots walk into a restaurant.... Feel free to finish\n@bstjr\n@coolderb\n@cnn\n@HarmoniousLivn\nhttps://t.co/2BMxHDvjJR",
        "geo": {
            "place_id": "fe4b2b8e51cc85c1"
        }
    },
    {
        "lang": "en",
        "public_metrics": {
            "retweet_count": 0,
            "reply_count": 0,
            "like_count": 0,
            "quote_count": 0
        },
        "author_id": "37313227",
        "geo": {
            "coordinates": {
                "type": "Point",
                "coordinates": [
                    -84.5791,
                    33.8187
                ]
            },
            "place_id": "fe4b2b8e51cc85c1"
        },
        "id": "1262871234431377409",
        "created_at": "2020-05-19T22:22:19.000Z",
        "edit_history_tweet_ids": [
            "1262871234431377409"
        ],
        "text": "I\u2019m outside an no I\u2019m not telling yal where I\u2019m at because if they reach social distancing capacity they close the bar it can only be 3 people at the bar at a time to have 6ft an they only got 6 tables on da patio\u2026 https://t.co/JcjIcFhIfw"
    },
    {
        "lang": "en",
        "public_metrics": {
            "retweet_count": 0,
            "reply_count": 0,
            "like_count": 0,
            "quote_count": 0
        },
        "author_id": "47622850",
        "id": "1262452735716122624",
        "created_at": "2020-05-18T18:39:22.000Z",
        "edit_history_tweet_ids": [
            "1262452735716122624"
        ],
        "text": "Best story I've heard in a while.\n\nhttps://t.co/d5fqYsw6il",
        "geo": {
            "place_id": "fe4b2b8e51cc85c1"
        }
    },
    {
        "lang": "en",
        "public_metrics": {
            "retweet_count": 0,
            "reply_count": 0,
            "like_count": 0,
            "quote_count": 0
        },
        "author_id": "1636362595",
        "geo": {
            "coordinates": {
                "type": "Point",
                "coordinates": [
                    -84.5815105,
                    33.81774154
                ]
            },
            "place_id": "fe4b2b8e51cc85c1"
        },
        "id": "1261845035819192323",
        "created_at": "2020-05-17T02:24:35.000Z",
        "edit_history_tweet_ids": [
            "1261845035819192323"
        ],
        "text": "See how the do Taurus \u2649\ufe0f y\u2019all #queens4life @ Sky Restaurant Bar and Grill https://t.co/XRM01Fb5KW"
    },
    {
        "lang": "en",
        "public_metrics": {
            "retweet_count": 1,
            "reply_count": 0,
            "like_count": 1,
            "quote_count": 0
        },
        "author_id": "834274879386038278",
        "id": "1261806217267159040",
        "created_at": "2020-05-16T23:50:20.000Z",
        "edit_history_tweet_ids": [
            "1261806217267159040"
        ],
        "text": "when i tell y\u2019all cafe social house breakfast be so good \ud83e\udd7a",
        "geo": {
            "place_id": "fe4b2b8e51cc85c1"
        }
    },
    {
        "lang": "en",
        "public_metrics": {
            "retweet_count": 1,
            "reply_count": 0,
            "like_count": 1,
            "quote_count": 0
        },
        "author_id": "1865111630",
        "id": "1261793996319477760",
        "created_at": "2020-05-16T23:01:46.000Z",
        "edit_history_tweet_ids": [
            "1261793996319477760"
        ],
        "text": "i miss the auntie\u2019s in the cafe. auntie hattie who always had the sandwiches on point\ud83e\udd27\ud83d\ude22 until next time auntie \ud83d\udc9c\ud83d\udc9b https://t.co/T3yW8KAOul",
        "geo": {
            "place_id": "fe4b2b8e51cc85c1"
        }
    },
    {
        "lang": "und",
        "public_metrics": {
            "retweet_count": 0,
            "reply_count": 0,
            "like_count": 0,
            "quote_count": 0
        },
        "author_id": "47622850",
        "id": "1261689547047526402",
        "created_at": "2020-05-16T16:06:43.000Z",
        "edit_history_tweet_ids": [
            "1261689547047526402"
        ],
        "text": ".... Sad\n\nhttps://t.co/bWsUc0tk90",
        "geo": {
            "place_id": "fe4b2b8e51cc85c1"
        }
    },
    {
        "lang": "en",
        "public_metrics": {
            "retweet_count": 2,
            "reply_count": 0,
            "like_count": 0,
            "quote_count": 0
        },
        "author_id": "30190594",
        "geo": {
            "coordinates": {
                "type": "Point",
                "coordinates": [
                    -84.51574708,
                    33.79953002
                ]
            },
            "place_id": "fe4b2b8e51cc85c1"
        },
        "id": "1261012513384206339",
        "created_at": "2020-05-14T19:16:26.000Z",
        "edit_history_tweet_ids": [
            "1261012513384206339"
        ],
        "text": "I\u2019m not single. I\u2019m in a long term relationship with action, adventure and fun. \ud83d\udcaf\u2708\ufe0f\ud83c\udfd6 \n.\n.\n.\n#adventure #fun #travel #lovingme @ Cafe' Social House https://t.co/RaC3C7NjPp"
    },
    {
        "lang": "en",
        "public_metrics": {
            "retweet_count": 2,
            "reply_count": 0,
            "like_count": 1,
            "quote_count": 0
        },
        "author_id": "250368700",
        "id": "1258501342173302786",
        "created_at": "2020-05-07T20:57:56.000Z",
        "edit_history_tweet_ids": [
            "1258501342173302786"
        ],
        "text": "Bar drunk is a mood",
        "geo": {
            "place_id": "fe4b2b8e51cc85c1"
        }
    },
    {
        "lang": "en",
        "public_metrics": {
            "retweet_count": 22,
            "reply_count": 8,
            "like_count": 158,
            "quote_count": 4
        },
        "author_id": "243749379",
        "id": "1253743439394623498",
        "created_at": "2020-04-24T17:51:44.000Z",
        "edit_history_tweet_ids": [
            "1253743439394623498"
        ],
        "text": "love the new look of our restaurant \u263a\ufe0f https://t.co/R0gNFdmZZx",
        "geo": {
            "place_id": "0fc3412bb6155001"
        }
    },
    {
        "lang": "en",
        "public_metrics": {
            "retweet_count": 0,
            "reply_count": 0,
            "like_count": 1,
            "quote_count": 0
        },
        "author_id": "47622850",
        "id": "1252236519009591296",
        "created_at": "2020-04-20T14:03:46.000Z",
        "edit_history_tweet_ids": [
            "1252236519009591296"
        ],
        "text": "Put these \"Americans\" in jail in general population. That will fix that.\n@cnn\n@coolderb\n@HarmoniousLivn\nhttps://t.co/yMJXv0mjJm",
        "geo": {
            "place_id": "fe4b2b8e51cc85c1"
        }
    },
    {
        "lang": "en",
        "public_metrics": {
            "retweet_count": 0,
            "reply_count": 2,
            "like_count": 7,
            "quote_count": 0
        },
        "author_id": "10228782",
        "id": "1250980376459251712",
        "created_at": "2020-04-17T02:52:18.000Z",
        "edit_history_tweet_ids": [
            "1250980376459251712"
        ],
        "text": "Incentives matter. Why would banks spend time with small businesses when they can originate $10 million loans for restaurant franchise groups?\n\nNo wonder almost none of the actual small businesses I know we're able to get a #PPPloan https://t.co/j60d7c03f4",
        "geo": {
            "place_id": "fe4b2b8e51cc85c1"
        }
    },
    {
        "lang": "en",
        "public_metrics": {
            "retweet_count": 1,
            "reply_count": 0,
            "like_count": 2,
            "quote_count": 0
        },
        "author_id": "1865111630",
        "id": "1250455686363963393",
        "created_at": "2020-04-15T16:07:22.000Z",
        "edit_history_tweet_ids": [
            "1250455686363963393"
        ],
        "text": "stepping back on camp , bouta go to the cafe https://t.co/nryQn3SPV0",
        "geo": {
            "place_id": "fe4b2b8e51cc85c1"
        }
    },
    {
        "lang": "en",
        "public_metrics": {
            "retweet_count": 0,
            "reply_count": 0,
            "like_count": 0,
            "quote_count": 0
        },
        "author_id": "250368700",
        "id": "1249332700030414849",
        "created_at": "2020-04-12T13:45:01.000Z",
        "edit_history_tweet_ids": [
            "1249332700030414849"
        ],
        "text": "I\u2019m going to Franchise a restaurant chain soon",
        "geo": {
            "place_id": "fe4b2b8e51cc85c1"
        }
    },
    {
        "lang": "en",
        "public_metrics": {
            "retweet_count": 0,
            "reply_count": 1,
            "like_count": 2,
            "quote_count": 0
        },
        "author_id": "15892715",
        "id": "1242980135386693632",
        "created_at": "2020-03-26T01:02:12.000Z",
        "edit_history_tweet_ids": [
            "1242980135386693632"
        ],
        "text": "@JMUJONMAC I have a restaurant routine. Always rare beef. An order in which I put the herbs, veggies &amp; noodles. NOT the same at home.\n\nSo I got chicken pho for take-out once. Game changer. It\u2019s now my take-out routine. The perk? I still get pho w/o messing up my \u201cexperience.\u201d https://t.co/3HpjSupc1g",
        "geo": {
            "place_id": "fe4b2b8e51cc85c1"
        }
    },
    {
        "lang": "en",
        "public_metrics": {
            "retweet_count": 0,
            "reply_count": 0,
            "like_count": 1,
            "quote_count": 0
        },
        "author_id": "613923729",
        "geo": {
            "coordinates": {
                "type": "Point",
                "coordinates": [
                    -84.58088636,
                    33.81782344
                ]
            },
            "place_id": "fe4b2b8e51cc85c1"
        },
        "id": "1241772197389185027",
        "created_at": "2020-03-22T17:02:17.000Z",
        "edit_history_tweet_ids": [
            "1241772197389185027"
        ],
        "text": "We are your healthy choice option.  Please call your order in to aide in your ordering process and ask about  our cashapp option to support our grab and go process. @ Paradise Smoothie Juice Bar https://t.co/cMw4xfG5ch"
    },
    {
        "lang": "en",
        "public_metrics": {
            "retweet_count": 0,
            "reply_count": 0,
            "like_count": 0,
            "quote_count": 0
        },
        "author_id": "1636362595",
        "geo": {
            "coordinates": {
                "type": "Point",
                "coordinates": [
                    -84.5815105,
                    33.81774154
                ]
            },
            "place_id": "fe4b2b8e51cc85c1"
        },
        "id": "1241469623238787080",
        "created_at": "2020-03-21T20:59:58.000Z",
        "edit_history_tweet_ids": [
            "1241469623238787080"
        ],
        "text": "Tonight... Early Set 8pm - 12am Pull Up Quick!!! #austell #checkthetagline @ Sky Restaurant Bar and Grill https://t.co/zhHbobqD2N"
    },
    {
        "lang": "en",
        "public_metrics": {
            "retweet_count": 0,
            "reply_count": 0,
            "like_count": 0,
            "quote_count": 0
        },
        "author_id": "47622850",
        "id": "1240363722398449669",
        "created_at": "2020-03-18T19:45:30.000Z",
        "edit_history_tweet_ids": [
            "1240363722398449669"
        ],
        "text": "Kemp is an idiot.. Just like his master 45\n\nhttps://t.co/Eow7ndxNE5",
        "geo": {
            "place_id": "fe4b2b8e51cc85c1"
        }
    },
    {
        "lang": "en",
        "public_metrics": {
            "retweet_count": 4,
            "reply_count": 1,
            "like_count": 7,
            "quote_count": 0
        },
        "author_id": "3304597723",
        "id": "1238659818380017665",
        "created_at": "2020-03-14T02:54:48.000Z",
        "edit_history_tweet_ids": [
            "1238659818380017665"
        ],
        "text": "\u201cHe CoPieD mY WHoLe FuKInG fLoW!!! WorD FOr wORd, BAr foR baR!!\u201d https://t.co/dU6nV55PNP",
        "geo": {
            "place_id": "fe4b2b8e51cc85c1"
        }
    },
    {
        "public_metrics": {
            "retweet_count": 0,
            "reply_count": 0,
            "like_count": 1,
            "quote_count": 0
        },
        "geo": {
            "place_id": "5b8df26e6d0be60b",
            "coordinates": {
                "type": "Point",
                "coordinates": [
                    -84.51335372,
                    33.79971077
                ]
            }
        },
        "author_id": "941358134127415299",
        "created_at": "2020-03-08T21:48:38.000Z",
        "id": "1236770831390461952",
        "lang": "en",
        "text": "Infusions are our thang here Margarita filled Skrrrawberries are available \n#sluttybrownies #atlantabakery #sweetsbysweetz #sweettooth #sweetdreams #sweettreats #brownies #cupcakes #cakes #atlanta #bakery #baker\u2026 https://t.co/wj76YNAvjF",
        "edit_history_tweet_ids": [
            "1236770831390461952"
        ]
    },
    {
        "public_metrics": {
            "retweet_count": 0,
            "reply_count": 0,
            "like_count": 1,
            "quote_count": 0
        },
        "geo": {
            "place_id": "5b8df26e6d0be60b",
            "coordinates": {
                "type": "Point",
                "coordinates": [
                    -84.51335372,
                    33.79971077
                ]
            }
        },
        "author_id": "941358134127415299",
        "created_at": "2020-03-08T19:08:37.000Z",
        "id": "1236730559818326019",
        "lang": "en",
        "text": "IF HUSTLE#IN WAS A CURSE I THINK I WOULD BE FUCKED SO GOOD\ud83e\udd37\ud83c\udffe\u200d\u2642\ufe0f SO WE GOT A BAKERY GRAND OPENING COMIN THIS FALL SHOP WITH UR FOLKS I SWEAR U WONT BE LET DOWN  \n#sluttybrownies #atlantabakery #sweetsbysweetz\u2026 https://t.co/oLQ2lYquIT",
        "edit_history_tweet_ids": [
            "1236730559818326019"
        ]
    },
    {
        "public_metrics": {
            "retweet_count": 0,
            "reply_count": 0,
            "like_count": 0,
            "quote_count": 0
        },
        "geo": {
            "place_id": "fe4b2b8e51cc85c1"
        },
        "author_id": "250368700",
        "created_at": "2020-03-06T22:04:52.000Z",
        "id": "1236050140328349696",
        "lang": "en",
        "text": "I wanna go to a bar crawl, looks fun",
        "edit_history_tweet_ids": [
            "1236050140328349696"
        ]
    },
    {
        "public_metrics": {
            "retweet_count": 0,
            "reply_count": 1,
            "like_count": 0,
            "quote_count": 0
        },
        "geo": {
            "place_id": "fe4b2b8e51cc85c1"
        },
        "author_id": "47622850",
        "created_at": "2020-03-04T01:11:32.000Z",
        "id": "1235009953359855616",
        "lang": "zxx",
        "text": "https://t.co/d2JFta1dc3",
        "edit_history_tweet_ids": [
            "1235009953359855616"
        ]
    },
    {
        "public_metrics": {
            "retweet_count": 0,
            "reply_count": 0,
            "like_count": 0,
            "quote_count": 0
        },
        "geo": {
            "place_id": "fe4b2b8e51cc85c1",
            "coordinates": {
                "type": "Point",
                "coordinates": [
                    -84.5815105,
                    33.81774154
                ]
            }
        },
        "author_id": "38971623",
        "created_at": "2020-03-02T17:09:08.000Z",
        "id": "1234526165815169024",
        "lang": "en",
        "text": "When your day ones turn into infinity and beyond \ud83d\ude80 \ud83d\udcab \u2b50\ufe0f #tomandjerry #saltandvinegar #jesusandchrist #baldandhead #earandring #bootyandcheek @ Sky Restaurant Bar and Grill https://t.co/rkzCTl5jsK",
        "edit_history_tweet_ids": [
            "1234526165815169024"
        ]
    },
    {
        "public_metrics": {
            "retweet_count": 0,
            "reply_count": 0,
            "like_count": 0,
            "quote_count": 0
        },
        "geo": {
            "place_id": "fe4b2b8e51cc85c1",
            "coordinates": {
                "type": "Point",
                "coordinates": [
                    -84.5815105,
                    33.81774154
                ]
            }
        },
        "author_id": "38971623",
        "created_at": "2020-03-01T17:52:50.000Z",
        "id": "1234174771530752001",
        "lang": "en",
        "text": "Happy Birthday lil bro love you man..... #themwingswascrack #hookahtastedlikeratlegs #yousmelledlikeconstructionworkerbooty #imoldnow #myfeethurt @ Sky Restaurant Bar and Grill https://t.co/CPWvK0m8vg",
        "edit_history_tweet_ids": [
            "1234174771530752001"
        ]
    },
    {
        "public_metrics": {
            "retweet_count": 0,
            "reply_count": 0,
            "like_count": 0,
            "quote_count": 0
        },
        "geo": {
            "place_id": "fe4b2b8e51cc85c1"
        },
        "author_id": "403455481",
        "created_at": "2020-03-01T06:59:29.000Z",
        "id": "1234010351278206977",
        "lang": "en",
        "text": "So nobody peeped @Drake using an @Eminem bar word for in when to say when",
        "edit_history_tweet_ids": [
            "1234010351278206977"
        ]
    },
    {
        "public_metrics": {
            "retweet_count": 0,
            "reply_count": 0,
            "like_count": 0,
            "quote_count": 0
        },
        "geo": {
            "place_id": "fe4b2b8e51cc85c1"
        },
        "author_id": "250368700",
        "created_at": "2020-02-24T15:18:54.000Z",
        "id": "1231961708199120898",
        "lang": "en",
        "text": "I\u2019m tryna go to Atlanta breakfast club restaurant, I love they food",
        "edit_history_tweet_ids": [
            "1231961708199120898"
        ]
    },
    {
        "public_metrics": {
            "retweet_count": 0,
            "reply_count": 2,
            "like_count": 1,
            "quote_count": 1
        },
        "geo": {
            "place_id": "fe4b2b8e51cc85c1"
        },
        "author_id": "250368700",
        "created_at": "2020-02-23T01:39:49.000Z",
        "id": "1231393192618201088",
        "lang": "en",
        "text": "I wanna go to kandi from #RHOA Restaurant",
        "edit_history_tweet_ids": [
            "1231393192618201088"
        ]
    },
    {
        "public_metrics": {
            "retweet_count": 0,
            "reply_count": 0,
            "like_count": 0,
            "quote_count": 0
        },
        "geo": {
            "place_id": "fe4b2b8e51cc85c1",
            "coordinates": {
                "type": "Point",
                "coordinates": [
                    -84.5815105,
                    33.81774154
                ]
            }
        },
        "author_id": "1636362595",
        "created_at": "2020-02-16T03:09:15.000Z",
        "id": "1228878982080233472",
        "lang": "en",
        "text": "Currently #pitstop #pullup @ Sky Restaurant Bar and Grill https://t.co/dXle0TFqCa",
        "edit_history_tweet_ids": [
            "1228878982080233472"
        ]
    },
    {
        "public_metrics": {
            "retweet_count": 0,
            "reply_count": 1,
            "like_count": 2,
            "quote_count": 0
        },
        "geo": {
            "place_id": "fe4b2b8e51cc85c1"
        },
        "author_id": "250368700",
        "created_at": "2020-02-14T01:45:43.000Z",
        "id": "1228133185323720712",
        "lang": "en",
        "text": "According to NASA if you balance a bar of soap on a rag ya ass won\u2019t stink .",
        "edit_history_tweet_ids": [
            "1228133185323720712"
        ]
    },
    {
        "public_metrics": {
            "retweet_count": 0,
            "reply_count": 0,
            "like_count": 0,
            "quote_count": 0
        },
        "geo": {
            "place_id": "fe4b2b8e51cc85c1",
            "coordinates": {
                "type": "Point",
                "coordinates": [
                    -84.579894,
                    33.817322
                ]
            }
        },
        "author_id": "341853215",
        "created_at": "2020-02-06T02:17:11.000Z",
        "id": "1225241999571406848",
        "lang": "en",
        "text": "Day 36. Military Lifts. These techniques used for training soldiers! 2 sets of 3 reps using 50lb dumbbells and 135lb bar! @ Planet Fitness https://t.co/lvuoGyOQeQ",
        "edit_history_tweet_ids": [
            "1225241999571406848"
        ]
    },
    {
        "public_metrics": {
            "retweet_count": 0,
            "reply_count": 0,
            "like_count": 0,
            "quote_count": 0
        },
        "geo": {
            "place_id": "fe4b2b8e51cc85c1"
        },
        "author_id": "318059553",
        "created_at": "2020-02-05T02:39:24.000Z",
        "id": "1224885201744138241",
        "lang": "en",
        "text": "I wanna go to a bar \ud83d\ude2d",
        "edit_history_tweet_ids": [
            "1224885201744138241"
        ]
    },
    {
        "public_metrics": {
            "retweet_count": 0,
            "reply_count": 0,
            "like_count": 0,
            "quote_count": 0
        },
        "geo": {
            "place_id": "fe4b2b8e51cc85c1",
            "coordinates": {
                "type": "Point",
                "coordinates": [
                    -84.5815105,
                    33.81774154
                ]
            }
        },
        "author_id": "1236576242",
        "created_at": "2020-02-02T05:32:10.000Z",
        "id": "1223841517606928386",
        "lang": "en",
        "text": "Out in those ATL Streets!! @ Sky Restaurant Bar and Grill https://t.co/L4WxjCB78h",
        "edit_history_tweet_ids": [
            "1223841517606928386"
        ]
    },
    {
        "public_metrics": {
            "retweet_count": 0,
            "reply_count": 0,
            "like_count": 0,
            "quote_count": 0
        },
        "geo": {
            "place_id": "fe4b2b8e51cc85c1",
            "coordinates": {
                "type": "Point",
                "coordinates": [
                    -84.5815105,
                    33.81774154
                ]
            }
        },
        "author_id": "1236576242",
        "created_at": "2020-02-02T05:32:04.000Z",
        "id": "1223841494022230016",
        "lang": "en",
        "text": "Yup got me a Hookah in the ATL @ Sky Restaurant Bar and Grill https://t.co/0X8ciE9ORP",
        "edit_history_tweet_ids": [
            "1223841494022230016"
        ]
    },
    {
        "public_metrics": {
            "retweet_count": 0,
            "reply_count": 0,
            "like_count": 2,
            "quote_count": 0
        },
        "geo": {
            "place_id": "fe4b2b8e51cc85c1"
        },
        "author_id": "3250102350",
        "created_at": "2020-01-26T12:27:09.000Z",
        "id": "1221409237190021120",
        "lang": "en",
        "text": "#Oprah spotted at Atlanta cafe ahead of wellness tour\n\n#atlchat\n\n#Oprahs2020VisionTour\n\n#oprahwinfry\n\n#busybeecafe\n\n#westsideatl\n\n#statefarmarena\n\n#downtownatl\n\nhttps://t.co/1QOewLOWux\n\nSent from my LGE LM-X420",
        "edit_history_tweet_ids": [
            "1221409237190021120"
        ]
    },
    {
        "public_metrics": {
            "retweet_count": 0,
            "reply_count": 1,
            "like_count": 0,
            "quote_count": 0
        },
        "geo": {
            "place_id": "fe4b2b8e51cc85c1"
        },
        "author_id": "273172592",
        "created_at": "2020-01-20T01:36:02.000Z",
        "id": "1219071050840932352",
        "lang": "en",
        "text": "@zchillin It\u2019s a restaurant!",
        "edit_history_tweet_ids": [
            "1219071050840932352"
        ]
    },
    {
        "public_metrics": {
            "retweet_count": 0,
            "reply_count": 0,
            "like_count": 0,
            "quote_count": 0
        },
        "geo": {
            "place_id": "fe4b2b8e51cc85c1"
        },
        "author_id": "2663505169",
        "created_at": "2020-01-18T18:56:26.000Z",
        "id": "1218608099029913602",
        "lang": "en",
        "text": "the restaurant looks so good wowww",
        "edit_history_tweet_ids": [
            "1218608099029913602"
        ]
    },
    {
        "public_metrics": {
            "retweet_count": 0,
            "reply_count": 0,
            "like_count": 0,
            "quote_count": 0
        },
        "geo": {
            "place_id": "fe4b2b8e51cc85c1",
            "coordinates": {
                "type": "Point",
                "coordinates": [
                    -84.5815105,
                    33.81774154
                ]
            }
        },
        "author_id": "1636362595",
        "created_at": "2020-01-12T04:58:24.000Z",
        "id": "1216222873775476736",
        "lang": "en",
        "text": "Currently #premiereentertainmentatlanta #927music #djrichsample @ Sky Restaurant Bar and Grill https://t.co/k9qttBemRr",
        "edit_history_tweet_ids": [
            "1216222873775476736"
        ]
    },
    {
        "public_metrics": {
            "retweet_count": 0,
            "reply_count": 0,
            "like_count": 2,
            "quote_count": 0
        },
        "geo": {
            "place_id": "fe4b2b8e51cc85c1"
        },
        "author_id": "2663505169",
        "created_at": "2020-01-08T19:58:03.000Z",
        "id": "1214999729261686784",
        "lang": "en",
        "text": "i\u2019m so happy my dad finally got to remodel the restaurant \ud83e\udd7a",
        "edit_history_tweet_ids": [
            "1214999729261686784"
        ]
    },
    {
        "public_metrics": {
            "retweet_count": 0,
            "reply_count": 2,
            "like_count": 1,
            "quote_count": 0
        },
        "geo": {
            "place_id": "fe4b2b8e51cc85c1"
        },
        "author_id": "250368700",
        "created_at": "2020-01-07T19:56:17.000Z",
        "id": "1214636894807560192",
        "lang": "en",
        "text": "I wanna go to kandi for #RHOA restaurant , food good af",
        "edit_history_tweet_ids": [
            "1214636894807560192"
        ]
    },
    {
        "public_metrics": {
            "retweet_count": 0,
            "reply_count": 0,
            "like_count": 0,
            "quote_count": 0
        },
        "geo": {
            "place_id": "fe4b2b8e51cc85c1"
        },
        "author_id": "889273660984487936",
        "created_at": "2020-01-05T07:59:54.000Z",
        "id": "1213731835122991105",
        "lang": "en",
        "text": "@brook1e_ @OrangeSliced U put arrows on ur hot bar?",
        "edit_history_tweet_ids": [
            "1213731835122991105"
        ]
    }
]