[
    {
        "text": "Looks like ima be In Houston by my dam self \ud83d\ude29 it\u2019s okay I can bar hop an sight see this should be fun \ud83d\ude02",
        "edit_history_tweet_ids": [
            "1531399249023406082"
        ],
        "lang": "en",
        "created_at": "2022-05-30T22:16:47.000Z",
        "geo": {
            "place_id": "2aacaaae6a17755c"
        },
        "author_id": "313446513",
        "public_metrics": {
            "retweet_count": 0,
            "reply_count": 0,
            "like_count": 0,
            "quote_count": 0
        },
        "id": "1531399249023406082"
    },
    {
        "text": "Sipping not dranking @ Bigelow's Bar &amp; Grill https://t.co/FKBuJTOE4p",
        "edit_history_tweet_ids": [
            "1531339941229105152"
        ],
        "lang": "en",
        "created_at": "2022-05-30T18:21:07.000Z",
        "geo": {
            "place_id": "2aacaaae6a17755c",
            "coordinates": {
                "type": "Point",
                "coordinates": [
                    -84.30996126,
                    33.71328619
                ]
            }
        },
        "author_id": "28740296",
        "public_metrics": {
            "retweet_count": 0,
            "reply_count": 0,
            "like_count": 0,
            "quote_count": 0
        },
        "id": "1531339941229105152"
    },
    {
        "text": "Ga Bar results came out today. that was the worst anticipation and stress i\u2019ve had yet",
        "edit_history_tweet_ids": [
            "1527708298463567874"
        ],
        "lang": "en",
        "created_at": "2022-05-20T17:50:16.000Z",
        "geo": {
            "place_id": "7202b2c7918d203e",
            "coordinates": {
                "type": "Point",
                "coordinates": [
                    -84.27507256,
                    33.71774292
                ]
            }
        },
        "author_id": "33181141",
        "public_metrics": {
            "retweet_count": 0,
            "reply_count": 1,
            "like_count": 0,
            "quote_count": 0
        },
        "id": "1527708298463567874"
    },
    {
        "text": "I think it's rude to finger somebody on a bar seat https://t.co/f7FbuokMf6",
        "edit_history_tweet_ids": [
            "1525193353255608325"
        ],
        "lang": "en",
        "created_at": "2022-05-13T19:16:46.000Z",
        "geo": {
            "place_id": "0a7dc9891a02c366"
        },
        "author_id": "1266433437352820738",
        "public_metrics": {
            "retweet_count": 6,
            "reply_count": 4,
            "like_count": 4,
            "quote_count": 1
        },
        "id": "1525193353255608325"
    },
    {
        "text": "Got my song played In Bigelows last night and got to perform it live\u2026 The blessings just keep coming.. ZONE 6..After 17 years IM BACK @ Bigelow's Bar &amp; Grill https://t.co/Hl3ZeyLyZj",
        "edit_history_tweet_ids": [
            "1524016110789697536"
        ],
        "lang": "en",
        "created_at": "2022-05-10T13:18:50.000Z",
        "geo": {
            "place_id": "2aacaaae6a17755c",
            "coordinates": {
                "type": "Point",
                "coordinates": [
                    -84.30996126,
                    33.71328619
                ]
            }
        },
        "author_id": "1511798474039255040",
        "public_metrics": {
            "retweet_count": 0,
            "reply_count": 0,
            "like_count": 0,
            "quote_count": 0
        },
        "id": "1524016110789697536"
    },
    {
        "text": "Just posted a photo @ Bigelow's Bar &amp; Grill https://t.co/h5DXdO5Lxs",
        "edit_history_tweet_ids": [
            "1517695007423143937"
        ],
        "lang": "en",
        "created_at": "2022-04-23T02:41:01.000Z",
        "geo": {
            "place_id": "2aacaaae6a17755c",
            "coordinates": {
                "type": "Point",
                "coordinates": [
                    -84.30996126,
                    33.71328619
                ]
            }
        },
        "author_id": "206054729",
        "public_metrics": {
            "retweet_count": 0,
            "reply_count": 0,
            "like_count": 0,
            "quote_count": 0
        },
        "id": "1517695007423143937"
    },
    {
        "text": "Just posted a photo @ Bigelow's Bar &amp; Grill https://t.co/jYQ7dZzFzq",
        "edit_history_tweet_ids": [
            "1517638792798158849"
        ],
        "lang": "en",
        "created_at": "2022-04-22T22:57:39.000Z",
        "geo": {
            "place_id": "2aacaaae6a17755c",
            "coordinates": {
                "type": "Point",
                "coordinates": [
                    -84.30996126,
                    33.71328619
                ]
            }
        },
        "author_id": "206054729",
        "public_metrics": {
            "retweet_count": 0,
            "reply_count": 0,
            "like_count": 0,
            "quote_count": 0
        },
        "id": "1517638792798158849"
    },
    {
        "text": "Hope her restaurant/club is doing well cause she won\u2019t be working in television or film no time soon \ud83d\ude44 Sometimes you have to know when you\u2019ve played the wrong hand. Take the L https://t.co/27mdypYsmy",
        "edit_history_tweet_ids": [
            "1517098625591033858"
        ],
        "lang": "en",
        "created_at": "2022-04-21T11:11:13.000Z",
        "geo": {
            "place_id": "2aacaaae6a17755c"
        },
        "author_id": "32171152",
        "public_metrics": {
            "retweet_count": 0,
            "reply_count": 0,
            "like_count": 0,
            "quote_count": 0
        },
        "id": "1517098625591033858"
    },
    {
        "text": "Best restaurant in Birmingham ?",
        "edit_history_tweet_ids": [
            "1514977686795522061"
        ],
        "lang": "fr",
        "created_at": "2022-04-15T14:43:22.000Z",
        "geo": {
            "place_id": "0a7dc9891a02c366"
        },
        "author_id": "1266433437352820738",
        "public_metrics": {
            "retweet_count": 0,
            "reply_count": 0,
            "like_count": 0,
            "quote_count": 1
        },
        "id": "1514977686795522061"
    },
    {
        "text": "spell restaurant without looking",
        "edit_history_tweet_ids": [
            "1514769072319250434"
        ],
        "lang": "en",
        "created_at": "2022-04-15T00:54:24.000Z",
        "geo": {
            "place_id": "2aacaaae6a17755c"
        },
        "author_id": "2557413516",
        "public_metrics": {
            "retweet_count": 0,
            "reply_count": 0,
            "like_count": 0,
            "quote_count": 0
        },
        "id": "1514769072319250434"
    },
    {
        "text": "@gymnasticsfluff Instead of Dylan\u2019s candy bar I\u2019m screaming",
        "edit_history_tweet_ids": [
            "1514606614921170958"
        ],
        "lang": "en",
        "created_at": "2022-04-14T14:08:51.000Z",
        "geo": {
            "place_id": "2aacaaae6a17755c"
        },
        "author_id": "1056205408501727232",
        "public_metrics": {
            "retweet_count": 0,
            "reply_count": 0,
            "like_count": 1,
            "quote_count": 0
        },
        "id": "1514606614921170958"
    },
    {
        "text": "Atp \ud83d\ude02 the bar is too fuckin low. I\u2019m too self sufficient for a nigga who can\u2019t meet me half way. I\u2019m not giving no cash up, no a nigga not moving in my shit, an I wish a mf would ask to drive my car. \ud83e\udd74 like no I\u2019m not that bitch. Those days BEEN gone.",
        "edit_history_tweet_ids": [
            "1512274631637577731"
        ],
        "lang": "en",
        "created_at": "2022-04-08T03:42:23.000Z",
        "geo": {
            "place_id": "2aacaaae6a17755c"
        },
        "author_id": "313446513",
        "public_metrics": {
            "retweet_count": 5,
            "reply_count": 0,
            "like_count": 9,
            "quote_count": 0
        },
        "id": "1512274631637577731"
    },
    {
        "text": "Bout to see what Bar Taco hitting on \ud83c\udf2e\ud83e\udd43",
        "edit_history_tweet_ids": [
            "1510041509722300421"
        ],
        "lang": "en",
        "created_at": "2022-04-01T23:48:45.000Z",
        "geo": {
            "place_id": "0a7dc9891a02c366"
        },
        "author_id": "88514593",
        "public_metrics": {
            "retweet_count": 0,
            "reply_count": 0,
            "like_count": 0,
            "quote_count": 0
        },
        "id": "1510041509722300421"
    },
    {
        "text": "Come and support @onyxsoutheast at our Monthly Bar Night Tomorrow night at the Hideaway from 10pm - 1am! Grab a drank, get some Jell-O shots, and have a good time. https://t.co/VMnBMdmnL5",
        "edit_history_tweet_ids": [
            "1509677213255352334"
        ],
        "lang": "en",
        "created_at": "2022-03-31T23:41:10.000Z",
        "geo": {
            "place_id": "0a7dc9891a02c366"
        },
        "author_id": "42289581",
        "public_metrics": {
            "retweet_count": 7,
            "reply_count": 0,
            "like_count": 23,
            "quote_count": 0
        },
        "id": "1509677213255352334"
    },
    {
        "text": "Atlanta really has a lot of love for #Prince! He's literally on the walls of restaurants or featured in different places! Spotted at Jojo's Beloved. A vinyl and cocktail lounge bar with amazing vibes....and they play not Purple Rain songs too!\n\n\ud83d\udcf7 https://t.co/zzny6fNDEL https://t.co/qTpIc0L68n",
        "edit_history_tweet_ids": [
            "1505713046022500354"
        ],
        "lang": "en",
        "created_at": "2022-03-21T01:08:59.000Z",
        "geo": {
            "place_id": "2aacaaae6a17755c"
        },
        "author_id": "730180850814484480",
        "public_metrics": {
            "retweet_count": 0,
            "reply_count": 2,
            "like_count": 18,
            "quote_count": 0
        },
        "id": "1505713046022500354"
    },
    {
        "text": "Na , we can\u2019t chill. Ask me my favorite restaurant, favorite chill spot . But hell naw , I don\u2019t pull up .",
        "edit_history_tweet_ids": [
            "1500357470329397259"
        ],
        "lang": "en",
        "created_at": "2022-03-06T06:27:50.000Z",
        "geo": {
            "place_id": "0a7dc9891a02c366"
        },
        "author_id": "184571272",
        "public_metrics": {
            "retweet_count": 0,
            "reply_count": 1,
            "like_count": 0,
            "quote_count": 0
        },
        "id": "1500357470329397259"
    },
    {
        "text": "I just went to my homie from high school restaurant the other day. #SouthernQueenz. Food was good af",
        "edit_history_tweet_ids": [
            "1495059027021213699"
        ],
        "lang": "en",
        "created_at": "2022-02-19T15:33:43.000Z",
        "geo": {
            "place_id": "0a7dc9891a02c366"
        },
        "author_id": "1013444590970572801",
        "public_metrics": {
            "retweet_count": 0,
            "reply_count": 0,
            "like_count": 0,
            "quote_count": 0
        },
        "id": "1495059027021213699"
    },
    {
        "text": "Ouu Chile we got this whole restaurant rolling \ud83d\ude02 We gone laugh round this bitch",
        "edit_history_tweet_ids": [
            "1491589172301373441"
        ],
        "lang": "en",
        "created_at": "2022-02-10T01:45:45.000Z",
        "geo": {
            "place_id": "107cca43d9950000"
        },
        "author_id": "1025660274",
        "public_metrics": {
            "retweet_count": 0,
            "reply_count": 0,
            "like_count": 0,
            "quote_count": 0
        },
        "id": "1491589172301373441"
    },
    {
        "text": "@thetoidoll Who you going to a sports bar with \ud83e\udd14\ud83e\uddd0",
        "edit_history_tweet_ids": [
            "1491166677949874178"
        ],
        "lang": "en",
        "created_at": "2022-02-08T21:46:55.000Z",
        "geo": {
            "place_id": "0a7dc9891a02c366"
        },
        "author_id": "227166712",
        "public_metrics": {
            "retweet_count": 0,
            "reply_count": 1,
            "like_count": 0,
            "quote_count": 0
        },
        "id": "1491166677949874178"
    },
    {
        "text": "@FaulknerFocus @HARRISFAULKNER @jimmyfailla Girl bye!!! You went to the other side, your not invited to any more bar b qs!! Sound like a duck!!",
        "edit_history_tweet_ids": [
            "1491022638914801664"
        ],
        "lang": "en",
        "created_at": "2022-02-08T12:14:33.000Z",
        "geo": {
            "place_id": "0a7dc9891a02c366"
        },
        "author_id": "770263175786799104",
        "public_metrics": {
            "retweet_count": 0,
            "reply_count": 0,
            "like_count": 0,
            "quote_count": 0
        },
        "id": "1491022638914801664"
    },
    {
        "text": "Golden Corral is the \"I thought it was a fart, but I shit my pants\" of the restaurant chain community.",
        "edit_history_tweet_ids": [
            "1488634473566679044"
        ],
        "lang": "en",
        "created_at": "2022-02-01T22:04:50.000Z",
        "geo": {
            "place_id": "2aacaaae6a17755c"
        },
        "author_id": "1676722314",
        "public_metrics": {
            "retweet_count": 0,
            "reply_count": 0,
            "like_count": 1,
            "quote_count": 0
        },
        "id": "1488634473566679044"
    },
    {
        "text": "I skipped my workout today. After dropping that dam bar on my foot yesterday I\u2019m taking today off \ud83e\udd7a",
        "edit_history_tweet_ids": [
            "1485918900067971073"
        ],
        "lang": "en",
        "created_at": "2022-01-25T10:14:07.000Z",
        "geo": {
            "place_id": "2aacaaae6a17755c"
        },
        "author_id": "313446513",
        "public_metrics": {
            "retweet_count": 0,
            "reply_count": 0,
            "like_count": 0,
            "quote_count": 0
        },
        "id": "1485918900067971073"
    },
    {
        "text": "Not the gay bar \ud83e\udd23 #Euphoria",
        "edit_history_tweet_ids": [
            "1485436576897417218"
        ],
        "lang": "en",
        "created_at": "2022-01-24T02:17:32.000Z",
        "geo": {
            "place_id": "0a7dc9891a02c366"
        },
        "author_id": "42289581",
        "public_metrics": {
            "retweet_count": 0,
            "reply_count": 0,
            "like_count": 0,
            "quote_count": 0
        },
        "id": "1485436576897417218"
    },
    {
        "text": "But I gotta stop drinking , cause I don\u2019t know why I ordered all that damn food last night at the Bar\ud83d\ude02\ud83d\ude02\ud83d\ude02\ud83d\ude02\ud83d\ude02\ud83d\ude02\ud83d\ude02\ud83d\ude02\ud83d\ude02\ud83d\ude02\ud83d\ude02\ud83d\ude02",
        "edit_history_tweet_ids": [
            "1472655627331723272"
        ],
        "lang": "en",
        "created_at": "2021-12-19T19:50:36.000Z",
        "geo": {
            "place_id": "2aacaaae6a17755c"
        },
        "author_id": "1359586429832167425",
        "public_metrics": {
            "retweet_count": 0,
            "reply_count": 0,
            "like_count": 0,
            "quote_count": 0
        },
        "id": "1472655627331723272"
    },
    {
        "text": "Type the year you became a teenager  in the gif bar and post it https://t.co/6s3nI38q2K https://t.co/OQxm5NxMBH",
        "edit_history_tweet_ids": [
            "1464791972124803080"
        ],
        "lang": "en",
        "created_at": "2021-11-28T03:03:15.000Z",
        "geo": {
            "place_id": "0a7dc9891a02c366"
        },
        "author_id": "42289581",
        "public_metrics": {
            "retweet_count": 0,
            "reply_count": 0,
            "like_count": 0,
            "quote_count": 2
        },
        "id": "1464791972124803080"
    },
    {
        "text": "Celebration of THE LIFE OF @djarmond  Oh what a Night \ud83d\udc9e Don kicked off Sag Season with a  BANG\ud83d\udca5 #OSS #King #Birthday #DJarmond #NY #ATL #HBD \ud83c\udf82 #SAG @ Bigelow's Bar &amp; Grill https://t.co/CKG5MZIStM",
        "edit_history_tweet_ids": [
            "1463385011994857477"
        ],
        "lang": "en",
        "created_at": "2021-11-24T05:52:29.000Z",
        "geo": {
            "place_id": "2aacaaae6a17755c",
            "coordinates": {
                "type": "Point",
                "coordinates": [
                    -84.30996126,
                    33.71328619
                ]
            }
        },
        "author_id": "869996529414799361",
        "public_metrics": {
            "retweet_count": 0,
            "reply_count": 0,
            "like_count": 0,
            "quote_count": 0
        },
        "id": "1463385011994857477"
    },
    {
        "text": "My last bar night as President...",
        "edit_history_tweet_ids": [
            "1460443229690683393"
        ],
        "lang": "en",
        "created_at": "2021-11-16T03:02:54.000Z",
        "geo": {
            "place_id": "0a7dc9891a02c366"
        },
        "author_id": "42289581",
        "public_metrics": {
            "retweet_count": 0,
            "reply_count": 0,
            "like_count": 9,
            "quote_count": 0
        },
        "id": "1460443229690683393"
    },
    {
        "text": ".@ONYXSOUTHEAST bar night is scheduled for December 3rd, 2021 @ The Hideaway. There will be a toiletry drive for the LGBTQIA+ homeless youth who are housed through Lost-N-Found, a nonprofit organization. Please bring an item(s) to help someone in need:\n\nhttps://t.co/XdzyP3bM6U https://t.co/7uWdXsAOuM",
        "edit_history_tweet_ids": [
            "1460438841102422018"
        ],
        "lang": "en",
        "created_at": "2021-11-16T02:45:28.000Z",
        "geo": {
            "place_id": "0a7dc9891a02c366"
        },
        "author_id": "42289581",
        "public_metrics": {
            "retweet_count": 1,
            "reply_count": 0,
            "like_count": 5,
            "quote_count": 0
        },
        "id": "1460438841102422018"
    },
    {
        "text": "Went out of my way to find a black owned restaurant to take Brenda to and it ended up being the biggest disappointment. We had to get up and walk out. Atlanta is just too fucking ghetto and y\u2019all niggas need to be stopped. \ud83d\ude02",
        "edit_history_tweet_ids": [
            "1452408382284091401"
        ],
        "lang": "en",
        "created_at": "2021-10-24T22:55:17.000Z",
        "geo": {
            "place_id": "0a7dc9891a02c366"
        },
        "author_id": "1059671706590052353",
        "public_metrics": {
            "retweet_count": 0,
            "reply_count": 0,
            "like_count": 1,
            "quote_count": 0
        },
        "id": "1452408382284091401"
    },
    {
        "text": "Be There Or Head Bout It \ud83d\udc83\ud83c\udffd\ud83d\udeaa\ud83d\udd25\n$2 Tuesday @spotlifemovement \n2920 Ember dr @chitchat_reloaded \n\n#Wyba #PullUp #Atlanta #Explore\n#ChitChat #Lounge #Bar #Hookah @ ChitChat_Reloaded https://t.co/pyqTbgEmKt",
        "edit_history_tweet_ids": [
            "1445540982913519620"
        ],
        "lang": "en",
        "created_at": "2021-10-06T00:06:41.000Z",
        "geo": {
            "place_id": "0a7dc9891a02c366",
            "coordinates": {
                "type": "Point",
                "coordinates": [
                    -84.27056,
                    33.71305
                ]
            }
        },
        "author_id": "286502954",
        "public_metrics": {
            "retweet_count": 0,
            "reply_count": 0,
            "like_count": 0,
            "quote_count": 0
        },
        "id": "1445540982913519620"
    },
    {
        "text": "Lil hood bar. I love it here",
        "edit_history_tweet_ids": [
            "1436156059236904962"
        ],
        "lang": "en",
        "created_at": "2021-09-10T02:34:21.000Z",
        "geo": {
            "place_id": "2aacaaae6a17755c"
        },
        "author_id": "199434569",
        "public_metrics": {
            "retweet_count": 0,
            "reply_count": 0,
            "like_count": 0,
            "quote_count": 0
        },
        "id": "1436156059236904962"
    },
    {
        "text": "That Peach Cobbler Caf\u00e9 commercial makes me laugh every time I hear it. Ms. Ruby out here flexin on her cooking skills.",
        "edit_history_tweet_ids": [
            "1431212601980170242"
        ],
        "lang": "en",
        "created_at": "2021-08-27T11:10:49.000Z",
        "geo": {
            "place_id": "0a7dc9891a02c366"
        },
        "author_id": "42289581",
        "public_metrics": {
            "retweet_count": 1,
            "reply_count": 1,
            "like_count": 1,
            "quote_count": 0
        },
        "id": "1431212601980170242"
    },
    {
        "text": "#GHSoundBitesSweepstakes my fav restaurant is A town wings",
        "edit_history_tweet_ids": [
            "1425602751984177153"
        ],
        "lang": "en",
        "created_at": "2021-08-11T23:39:17.000Z",
        "geo": {
            "place_id": "0a7dc9891a02c366"
        },
        "author_id": "48437276",
        "public_metrics": {
            "retweet_count": 0,
            "reply_count": 0,
            "like_count": 0,
            "quote_count": 0
        },
        "id": "1425602751984177153"
    },
    {
        "text": "@bar_time14 It is so hot and muggy here in Atlanta!!",
        "edit_history_tweet_ids": [
            "1425174522882412545"
        ],
        "lang": "en",
        "created_at": "2021-08-10T19:17:39.000Z",
        "geo": {
            "place_id": "2aacaaae6a17755c"
        },
        "author_id": "789002952937771008",
        "public_metrics": {
            "retweet_count": 0,
            "reply_count": 0,
            "like_count": 0,
            "quote_count": 0
        },
        "id": "1425174522882412545"
    },
    {
        "text": "For the month of August only, check out our new S'mores Cookie filled with graham crackers, milk chocolate chips, and marshmallows, and topped with s\u2019more marshmallows and Hershey candy bar pieces. This cookie is insane!\n\nOrder today. Link in bio. https://t.co/yMk3J8Klbq",
        "edit_history_tweet_ids": [
            "1423296567935569922"
        ],
        "lang": "en",
        "created_at": "2021-08-05T14:55:20.000Z",
        "geo": {
            "place_id": "2aacaaae6a17755c"
        },
        "author_id": "1257021119623806976",
        "public_metrics": {
            "retweet_count": 2,
            "reply_count": 1,
            "like_count": 0,
            "quote_count": 0
        },
        "id": "1423296567935569922"
    },
    {
        "text": "So if you work at any restaurant here in Atlanta they are requiring people to have the vaccine before they can return to work\u203c\ufe0f If you haven't gotten the vaccine yet then you are required to do rapid testing twice a week \ud83e\udd37\ud83c\udffb\u200d\u2640\ufe0f My son is working outside at Google in South Carolina",
        "edit_history_tweet_ids": [
            "1422927074587725830"
        ],
        "lang": "en",
        "created_at": "2021-08-04T14:27:05.000Z",
        "geo": {
            "place_id": "2aacaaae6a17755c"
        },
        "author_id": "789002952937771008",
        "public_metrics": {
            "retweet_count": 0,
            "reply_count": 1,
            "like_count": 0,
            "quote_count": 0
        },
        "id": "1422927074587725830"
    },
    {
        "text": "Mind y\u2019all.. I ain\u2019t never been a server before or even worked in a restaurant \ud83d\udc80\ud83d\ude29 https://t.co/4SvO9rXY58",
        "edit_history_tweet_ids": [
            "1422204099907436551"
        ],
        "lang": "en",
        "created_at": "2021-08-02T14:34:15.000Z",
        "geo": {
            "place_id": "0a7dc9891a02c366"
        },
        "author_id": "926734340",
        "public_metrics": {
            "retweet_count": 0,
            "reply_count": 0,
            "like_count": 1,
            "quote_count": 0
        },
        "id": "1422204099907436551"
    },
    {
        "text": "They done put me back on the bar at Topgolf https://t.co/YE9070bKe3",
        "edit_history_tweet_ids": [
            "1417178494526803968"
        ],
        "lang": "en",
        "created_at": "2021-07-19T17:44:17.000Z",
        "geo": {
            "place_id": "0a7dc9891a02c366"
        },
        "author_id": "1284111748912549894",
        "public_metrics": {
            "retweet_count": 0,
            "reply_count": 1,
            "like_count": 1,
            "quote_count": 0
        },
        "id": "1417178494526803968"
    },
    {
        "text": "I can\u2019t wait till I get a home and build my bar in there \ud83d\ude2d",
        "edit_history_tweet_ids": [
            "1409699988947361800"
        ],
        "lang": "en",
        "created_at": "2021-06-29T02:27:22.000Z",
        "geo": {
            "place_id": "0a7dc9891a02c366"
        },
        "author_id": "821779500266618888",
        "public_metrics": {
            "retweet_count": 0,
            "reply_count": 0,
            "like_count": 0,
            "quote_count": 0
        },
        "id": "1409699988947361800"
    },
    {
        "text": "Bey fans dead ass wrong for them reviews on that man restaurant \ud83d\udc80\ud83d\udc80\ud83d\udc80",
        "edit_history_tweet_ids": [
            "1407482673203924992"
        ],
        "lang": "en",
        "created_at": "2021-06-22T23:36:33.000Z",
        "geo": {
            "place_id": "2aacaaae6a17755c"
        },
        "author_id": "913991597934743552",
        "public_metrics": {
            "retweet_count": 1,
            "reply_count": 0,
            "like_count": 0,
            "quote_count": 0
        },
        "id": "1407482673203924992"
    },
    {
        "text": "@SnickerzBites @africanintheus #A1 for Korean Bar B Que",
        "edit_history_tweet_ids": [
            "1400919716538073091"
        ],
        "lang": "en",
        "created_at": "2021-06-04T20:57:42.000Z",
        "geo": {
            "place_id": "0a7dc9891a02c366"
        },
        "author_id": "1027033849409273856",
        "public_metrics": {
            "retweet_count": 0,
            "reply_count": 0,
            "like_count": 0,
            "quote_count": 0
        },
        "id": "1400919716538073091"
    },
    {
        "text": "BodiGlaze will be a vendor at Reel Steel Sports Bar &amp; Grill this Saturday from 11am-4pm at 2565 Wesley Chapel Rd Decatur, GA 30035! Come out and support your local vendors. Hope to see you there! https://t.co/U6dUsrQlhH",
        "edit_history_tweet_ids": [
            "1392557561291984897"
        ],
        "lang": "en",
        "created_at": "2021-05-12T19:09:29.000Z",
        "geo": {
            "place_id": "0a7dc9891a02c366"
        },
        "author_id": "264738836",
        "public_metrics": {
            "retweet_count": 0,
            "reply_count": 0,
            "like_count": 1,
            "quote_count": 0
        },
        "id": "1392557561291984897"
    },
    {
        "text": "@DeAngeloMarquis I HATE YOU FOR THIS!!!!! \ud83d\ude02\n\nLet me get my Highland Bakery in peace!",
        "edit_history_tweet_ids": [
            "1392296139144183808"
        ],
        "lang": "en",
        "created_at": "2021-05-12T01:50:41.000Z",
        "geo": {
            "place_id": "0a7dc9891a02c366"
        },
        "author_id": "42289581",
        "public_metrics": {
            "retweet_count": 0,
            "reply_count": 1,
            "like_count": 1,
            "quote_count": 0
        },
        "id": "1392296139144183808"
    },
    {
        "text": "wanna go to the beltline today but the restaurant i wanna go to isn\u2019t open\ud83d\ude44",
        "edit_history_tweet_ids": [
            "1386383729346613252"
        ],
        "lang": "en",
        "created_at": "2021-04-25T18:16:53.000Z",
        "geo": {
            "place_id": "0a7dc9891a02c366"
        },
        "author_id": "168560949",
        "public_metrics": {
            "retweet_count": 0,
            "reply_count": 0,
            "like_count": 1,
            "quote_count": 0
        },
        "id": "1386383729346613252"
    },
    {
        "text": "@simply_lay_ @PrinceLandon_ That search bar \ud83d\ude2d\ud83d\ude2d\ud83d\ude2d",
        "edit_history_tweet_ids": [
            "1384626408690012166"
        ],
        "lang": "en",
        "created_at": "2021-04-20T21:53:55.000Z",
        "geo": {
            "place_id": "0a7dc9891a02c366"
        },
        "author_id": "2203755396",
        "public_metrics": {
            "retweet_count": 0,
            "reply_count": 1,
            "like_count": 41,
            "quote_count": 0
        },
        "id": "1384626408690012166"
    },
    {
        "text": "JJ\u2019s Fish &amp; Chicken plates be lookin like Cafe Du Monde beignets",
        "edit_history_tweet_ids": [
            "1373746542264340480"
        ],
        "lang": "en",
        "created_at": "2021-03-21T21:21:13.000Z",
        "geo": {
            "place_id": "0a7dc9891a02c366"
        },
        "author_id": "58722026",
        "public_metrics": {
            "retweet_count": 0,
            "reply_count": 1,
            "like_count": 1,
            "quote_count": 0
        },
        "id": "1373746542264340480"
    },
    {
        "text": "@vikkichance02 is in the house #eastatlanta @ Bigelow's Bar &amp; Grill https://t.co/7y0JkYibi0",
        "edit_history_tweet_ids": [
            "1370981068422139908"
        ],
        "lang": "en",
        "created_at": "2021-03-14T06:12:12.000Z",
        "geo": {
            "place_id": "2aacaaae6a17755c",
            "coordinates": {
                "type": "Point",
                "coordinates": [
                    -84.30996126,
                    33.71328619
                ]
            }
        },
        "author_id": "713166850188820480",
        "public_metrics": {
            "retweet_count": 0,
            "reply_count": 0,
            "like_count": 0,
            "quote_count": 0
        },
        "id": "1370981068422139908"
    },
    {
        "text": "gotta make some fast car music for deun - a bar",
        "edit_history_tweet_ids": [
            "1368655144162824194"
        ],
        "lang": "en",
        "created_at": "2021-03-07T20:09:49.000Z",
        "geo": {
            "place_id": "0a7dc9891a02c366"
        },
        "author_id": "464322884",
        "public_metrics": {
            "retweet_count": 1,
            "reply_count": 0,
            "like_count": 1,
            "quote_count": 0
        },
        "id": "1368655144162824194"
    },
    {
        "text": "@PhinsTweets @snooki She is on the new season, someone already leaked footage of her in the restaurant with Angelina having their 1st sit down since Snooki wedding...But it\u2019s being said she isn\u2019t full time, she will be part time",
        "edit_history_tweet_ids": [
            "1368045116120829952"
        ],
        "lang": "en",
        "created_at": "2021-03-06T03:45:47.000Z",
        "geo": {
            "place_id": "0a7dc9891a02c366"
        },
        "author_id": "59028057",
        "public_metrics": {
            "retweet_count": 0,
            "reply_count": 0,
            "like_count": 0,
            "quote_count": 0
        },
        "id": "1368045116120829952"
    },
    {
        "text": "Chef Linton Hopkins Halts Plans for His Forthcoming Restaurant Eugene and Elizabeth\u2019s https://t.co/Xlw2MLynEp",
        "edit_history_tweet_ids": [
            "1364975617310134272"
        ],
        "lang": "en",
        "created_at": "2021-02-25T16:28:41.000Z",
        "geo": {
            "place_id": "0a7dc9891a02c366"
        },
        "author_id": "999118172463616000",
        "public_metrics": {
            "retweet_count": 0,
            "reply_count": 0,
            "like_count": 0,
            "quote_count": 0
        },
        "id": "1364975617310134272"
    },
    {
        "text": "If you were my bartender Baby what would we talk about. Would you dress sexy and be friendly. Or would you ignore me and talk to the other guy at the end of the bar. Many bartenders have their favorite customers.",
        "edit_history_tweet_ids": [
            "1364761739984781314"
        ],
        "lang": "en",
        "created_at": "2021-02-25T02:18:49.000Z",
        "geo": {
            "place_id": "0a7dc9891a02c366"
        },
        "author_id": "999118172463616000",
        "public_metrics": {
            "retweet_count": 0,
            "reply_count": 0,
            "like_count": 0,
            "quote_count": 0
        },
        "id": "1364761739984781314"
    },
    {
        "public_metrics": {
            "retweet_count": 0,
            "reply_count": 0,
            "like_count": 0,
            "quote_count": 0
        },
        "geo": {
            "place_id": "0a7dc9891a02c366"
        },
        "author_id": "25327447",
        "created_at": "2021-02-13T02:29:53.000Z",
        "id": "1360415872523862017",
        "lang": "en",
        "text": "@Amy_Siskind I can\u2019t believe they are actually qualified to practice law! They work as though the only bar they passed was @Applebees !",
        "edit_history_tweet_ids": [
            "1360415872523862017"
        ]
    },
    {
        "public_metrics": {
            "retweet_count": 0,
            "reply_count": 0,
            "like_count": 0,
            "quote_count": 0
        },
        "geo": {
            "place_id": "0a7dc9891a02c366"
        },
        "author_id": "79196921",
        "created_at": "2021-02-11T13:47:57.000Z",
        "id": "1359861736896159745",
        "lang": "en",
        "text": "@tacobell your beans are absolutely disgusting. Before you worry any more about whether or not to serve potatoes try serving fresh made beans. @DelTaco please expand your restaurant to the Atlanta area!!!! You're one thing I miss about California \ud83d\ude1f",
        "edit_history_tweet_ids": [
            "1359861736896159745"
        ]
    },
    {
        "public_metrics": {
            "retweet_count": 0,
            "reply_count": 1,
            "like_count": 8,
            "quote_count": 0
        },
        "geo": {
            "place_id": "0a7dc9891a02c366"
        },
        "author_id": "42289581",
        "created_at": "2021-02-03T20:28:18.000Z",
        "id": "1357063383531589639",
        "lang": "en",
        "text": "I need this for my bar vest. https://t.co/dXI8nMST54",
        "edit_history_tweet_ids": [
            "1357063383531589639"
        ]
    },
    {
        "public_metrics": {
            "retweet_count": 0,
            "reply_count": 0,
            "like_count": 0,
            "quote_count": 0
        },
        "geo": {
            "place_id": "0a7dc9891a02c366"
        },
        "author_id": "1013444590970572801",
        "created_at": "2021-01-29T17:06:54.000Z",
        "id": "1355200762121478148",
        "lang": "en",
        "text": "Taking penitentiary chances with this one bar of gas. I\u2019ll stop at panola",
        "edit_history_tweet_ids": [
            "1355200762121478148"
        ]
    },
    {
        "public_metrics": {
            "retweet_count": 0,
            "reply_count": 0,
            "like_count": 0,
            "quote_count": 0
        },
        "geo": {
            "place_id": "2aacaaae6a17755c"
        },
        "author_id": "1266433437352820738",
        "created_at": "2021-01-20T20:47:43.000Z",
        "id": "1351994838749741064",
        "lang": "en",
        "text": "Legend's Cafe on old nat &gt;&gt;&gt;&gt;&gt;&gt;",
        "edit_history_tweet_ids": [
            "1351994838749741064"
        ]
    },
    {
        "public_metrics": {
            "retweet_count": 1,
            "reply_count": 0,
            "like_count": 0,
            "quote_count": 0
        },
        "geo": {
            "place_id": "0a7dc9891a02c366"
        },
        "author_id": "227166712",
        "created_at": "2021-01-16T14:10:41.000Z",
        "id": "1350445370359349251",
        "lang": "en",
        "text": "Thankfully there is a wing restaurant on every street corner because fuck that https://t.co/Gyr54YFJHw",
        "edit_history_tweet_ids": [
            "1350445370359349251"
        ]
    },
    {
        "public_metrics": {
            "retweet_count": 0,
            "reply_count": 0,
            "like_count": 0,
            "quote_count": 0
        },
        "geo": {
            "place_id": "0a7dc9891a02c366",
            "coordinates": {
                "type": "Point",
                "coordinates": [
                    -84.2720499,
                    33.71206
                ]
            }
        },
        "author_id": "249982779",
        "created_at": "2021-01-15T23:18:46.000Z",
        "id": "1350220914969997316",
        "lang": "en",
        "text": "KARIM jamal @ Nations Cafe Bodega https://t.co/QnDBl85gYJ",
        "edit_history_tweet_ids": [
            "1350220914969997316"
        ]
    },
    {
        "public_metrics": {
            "retweet_count": 0,
            "reply_count": 0,
            "like_count": 0,
            "quote_count": 0
        },
        "geo": {
            "place_id": "0a7dc9891a02c366"
        },
        "author_id": "84427534",
        "created_at": "2021-01-08T14:45:27.000Z",
        "id": "1347555016924659717",
        "lang": "en",
        "text": "@swavesevah  So are you gonna put yourself on Wack Bar of The Week?   \u201cI\u2019m winning this battle Claire/Clear, Cliff Huxtable.\u201d  Come on bruh \ud83e\udd37\ud83c\udffe\u200d\u2642\ufe0f",
        "edit_history_tweet_ids": [
            "1347555016924659717"
        ]
    },
    {
        "public_metrics": {
            "retweet_count": 0,
            "reply_count": 0,
            "like_count": 0,
            "quote_count": 0
        },
        "geo": {
            "place_id": "2aacaaae6a17755c",
            "coordinates": {
                "type": "Point",
                "coordinates": [
                    -84.30996126,
                    33.71328619
                ]
            }
        },
        "author_id": "28740296",
        "created_at": "2020-12-25T00:19:12.000Z",
        "id": "1342263591039356930",
        "lang": "en",
        "text": "Snow, tales Right @ Bigelow's Bar &amp; Grill https://t.co/0vTtR0ftY7",
        "edit_history_tweet_ids": [
            "1342263591039356930"
        ]
    },
    {
        "public_metrics": {
            "retweet_count": 1,
            "reply_count": 1,
            "like_count": 3,
            "quote_count": 0
        },
        "geo": {
            "place_id": "2aacaaae6a17755c"
        },
        "author_id": "1001239631055261697",
        "created_at": "2020-12-12T08:41:02.000Z",
        "id": "1337678839443501057",
        "lang": "en",
        "text": "S/o to @neesiemikare for the drinks !!! \n\nIf y\u2019all in ATL and like sushi go to RA &amp; sit at the bar with my sis",
        "edit_history_tweet_ids": [
            "1337678839443501057"
        ]
    },
    {
        "public_metrics": {
            "retweet_count": 0,
            "reply_count": 2,
            "like_count": 0,
            "quote_count": 0
        },
        "geo": {
            "place_id": "0a7dc9891a02c366"
        },
        "author_id": "42289581",
        "created_at": "2020-12-10T17:06:37.000Z",
        "id": "1337081296795918336",
        "lang": "en",
        "text": "@Gregs_Anatomy @YSL_Ron He really thought his dick and pics clearly taken in the early 00s was gonna be his in. \n\nThe bar is set in fucking hell.",
        "edit_history_tweet_ids": [
            "1337081296795918336"
        ]
    },
    {
        "public_metrics": {
            "retweet_count": 0,
            "reply_count": 0,
            "like_count": 0,
            "quote_count": 0
        },
        "text": "When The Heat On Imma Still Have On VLone @ Phat Phish Cafe LLC https://t.co/EvIfMGoW0m",
        "edit_history_tweet_ids": [
            "1332109022380613632"
        ],
        "geo": {
            "coordinates": {
                "type": "Point",
                "coordinates": [
                    -84.32261,
                    33.72554
                ]
            },
            "place_id": "8173485c72e78ca5"
        },
        "lang": "en",
        "created_at": "2020-11-26T23:48:34.000Z",
        "id": "1332109022380613632",
        "author_id": "634079899"
    },
    {
        "public_metrics": {
            "retweet_count": 0,
            "reply_count": 0,
            "like_count": 0,
            "quote_count": 0
        },
        "text": "Back to Fletchers. Big homie said she\u2019s back behind the bar so it\u2019s Frenchy time",
        "edit_history_tweet_ids": [
            "1323697365916766209"
        ],
        "lang": "en",
        "created_at": "2020-11-03T18:43:39.000Z",
        "id": "1323697365916766209",
        "geo": {
            "place_id": "0a7dc9891a02c366"
        },
        "author_id": "224007244"
    },
    {
        "public_metrics": {
            "retweet_count": 0,
            "reply_count": 1,
            "like_count": 0,
            "quote_count": 0
        },
        "text": "@ShaqAtwaters I\u2019m at the bar now!",
        "edit_history_tweet_ids": [
            "1323377538211684352"
        ],
        "lang": "en",
        "created_at": "2020-11-02T21:32:46.000Z",
        "id": "1323377538211684352",
        "geo": {
            "place_id": "0a7dc9891a02c366"
        },
        "author_id": "231720236"
    },
    {
        "public_metrics": {
            "retweet_count": 0,
            "reply_count": 1,
            "like_count": 0,
            "quote_count": 0
        },
        "text": "Better than that restaurant in ya pinned tweet? https://t.co/fanslLG0gH",
        "edit_history_tweet_ids": [
            "1317959853722247170"
        ],
        "lang": "en",
        "created_at": "2020-10-18T22:44:50.000Z",
        "id": "1317959853722247170",
        "geo": {
            "place_id": "0a7dc9891a02c366"
        },
        "author_id": "1266433437352820738"
    },
    {
        "public_metrics": {
            "retweet_count": 0,
            "reply_count": 0,
            "like_count": 0,
            "quote_count": 0
        },
        "text": "@jhpii #BackDay \nT Bar Row\nOne Arm Row\n\n#willpowerstrength #willpowersworkout #willpowerspersonaltraining #wphperforms #workout #grind #fitness #fitnessmotivation \n\n@wphperforms @ East Atlanta https://t.co/CLXpxNxBCT",
        "edit_history_tweet_ids": [
            "1315624311059775490"
        ],
        "geo": {
            "coordinates": {
                "type": "Point",
                "coordinates": [
                    -84.338041,
                    33.731196
                ]
            },
            "place_id": "8173485c72e78ca5"
        },
        "lang": "en",
        "created_at": "2020-10-12T12:04:13.000Z",
        "id": "1315624311059775490",
        "author_id": "244158159"
    },
    {
        "public_metrics": {
            "retweet_count": 0,
            "reply_count": 0,
            "like_count": 0,
            "quote_count": 0
        },
        "text": "@Aye_Fluke jacks pizza n wings , legends cafe",
        "edit_history_tweet_ids": [
            "1314782462657126400"
        ],
        "lang": "en",
        "created_at": "2020-10-10T04:19:01.000Z",
        "id": "1314782462657126400",
        "geo": {
            "place_id": "0a7dc9891a02c366"
        },
        "author_id": "464322884"
    },
    {
        "public_metrics": {
            "retweet_count": 0,
            "reply_count": 0,
            "like_count": 0,
            "quote_count": 0
        },
        "text": "Let's get it @ Bigelow's Bar &amp; Grill https://t.co/OXgCDIrLyE",
        "edit_history_tweet_ids": [
            "1314736476832366595"
        ],
        "geo": {
            "coordinates": {
                "type": "Point",
                "coordinates": [
                    -84.30996126,
                    33.71328619
                ]
            },
            "place_id": "2aacaaae6a17755c"
        },
        "lang": "en",
        "created_at": "2020-10-10T01:16:17.000Z",
        "id": "1314736476832366595",
        "author_id": "1316096010"
    },
    {
        "public_metrics": {
            "retweet_count": 0,
            "reply_count": 0,
            "like_count": 0,
            "quote_count": 0
        },
        "text": "If it\u2019s one thing I know how to do is find a restaurant",
        "edit_history_tweet_ids": [
            "1305578323465187328"
        ],
        "lang": "en",
        "created_at": "2020-09-14T18:45:03.000Z",
        "id": "1305578323465187328",
        "geo": {
            "place_id": "0a7dc9891a02c366"
        },
        "author_id": "1266433437352820738"
    },
    {
        "public_metrics": {
            "retweet_count": 0,
            "reply_count": 0,
            "like_count": 0,
            "quote_count": 0
        },
        "text": "y'all i really need help . this lady bumped into me at the bar i immediately took my purse of my shoulder and said \"BITCH ILL BEAT YO ASS IN HERE\" \n\nmy friends brought me home SO FUCKING FAST \ud83d\ude02\ud83d\ude02\ud83d\ude02",
        "edit_history_tweet_ids": [
            "1301360813219950598"
        ],
        "lang": "en",
        "created_at": "2020-09-03T03:26:10.000Z",
        "id": "1301360813219950598",
        "geo": {
            "place_id": "0a7dc9891a02c366"
        },
        "author_id": "175121215"
    },
    {
        "public_metrics": {
            "retweet_count": 0,
            "reply_count": 0,
            "like_count": 0,
            "quote_count": 0
        },
        "text": "It\u2019s only been 3 weeks at this new job and it\u2019s almost as dramatic as the bar I ain\u2019t at no more!",
        "edit_history_tweet_ids": [
            "1301227131616276481"
        ],
        "lang": "en",
        "created_at": "2020-09-02T18:34:58.000Z",
        "id": "1301227131616276481",
        "geo": {
            "place_id": "0a7dc9891a02c366"
        },
        "author_id": "2592175655"
    },
    {
        "public_metrics": {
            "retweet_count": 0,
            "reply_count": 0,
            "like_count": 5,
            "quote_count": 0
        },
        "text": "It\u2019s a shame that complete sentences, which is basic communication, peaks my interest so much on apps. \n\nThat\u2019s how low the bar is, basic communication skills are hard to come by.",
        "edit_history_tweet_ids": [
            "1298574855374331904"
        ],
        "lang": "en",
        "created_at": "2020-08-26T10:55:46.000Z",
        "id": "1298574855374331904",
        "geo": {
            "place_id": "0a7dc9891a02c366"
        },
        "author_id": "42289581"
    },
    {
        "public_metrics": {
            "retweet_count": 0,
            "reply_count": 0,
            "like_count": 0,
            "quote_count": 0
        },
        "text": "The bar is set so low. https://t.co/EjHcli5DHd",
        "edit_history_tweet_ids": [
            "1291583286284816385"
        ],
        "lang": "en",
        "created_at": "2020-08-07T03:53:46.000Z",
        "id": "1291583286284816385",
        "geo": {
            "place_id": "0a7dc9891a02c366"
        },
        "author_id": "42289581"
    },
    {
        "public_metrics": {
            "retweet_count": 0,
            "reply_count": 0,
            "like_count": 1,
            "quote_count": 0
        },
        "text": "FUNNY STORY !\nso i went for drinks with my coworkers after work and it was a car show outside the bar when we left \n\nI RECORDED IT AND MY COMMENTARY IS HILARIOUS AND SOOOOOO INAPPROPRIATE \ud83d\ude02\ud83e\udd23\n\ni cant even post it \ud83e\udd26\ud83c\udffe\u200d\u2640\ufe0f\nDon't Let Sie Get Drunk !!",
        "edit_history_tweet_ids": [
            "1290523727973801986"
        ],
        "lang": "en",
        "created_at": "2020-08-04T05:43:28.000Z",
        "id": "1290523727973801986",
        "geo": {
            "place_id": "0a7dc9891a02c366"
        },
        "author_id": "175121215"
    },
    {
        "public_metrics": {
            "retweet_count": 0,
            "reply_count": 0,
            "like_count": 0,
            "quote_count": 0
        },
        "text": "I have been accosted at work, on the street, in a bar, by men just like Rep. Yoho. I\u2019ve learned to have a thick skin and to let these men know I was not raised to take abuse! I refuse to be treated like I don\u2019t matter! https://t.co/MCzMus4BBd",
        "edit_history_tweet_ids": [
            "1286418577424371712"
        ],
        "lang": "en",
        "created_at": "2020-07-23T21:51:04.000Z",
        "id": "1286418577424371712",
        "geo": {
            "place_id": "0a7dc9891a02c366"
        },
        "author_id": "1076826479147790336"
    },
    {
        "public_metrics": {
            "retweet_count": 0,
            "reply_count": 1,
            "like_count": 1,
            "quote_count": 0
        },
        "text": "I\u2019m usually just trying to sneak and get my double chocolate cookie from Highland Bakery and I get caught lol. https://t.co/w3IT31qdVS",
        "edit_history_tweet_ids": [
            "1285404962848112641"
        ],
        "lang": "en",
        "created_at": "2020-07-21T02:43:19.000Z",
        "id": "1285404962848112641",
        "geo": {
            "place_id": "0a7dc9891a02c366"
        },
        "author_id": "42289581"
    },
    {
        "public_metrics": {
            "retweet_count": 0,
            "reply_count": 0,
            "like_count": 1,
            "quote_count": 0
        },
        "text": "The porn bar is set SO low for big dicked men. At least in Gay Porn anyway.",
        "edit_history_tweet_ids": [
            "1285321342938755074"
        ],
        "lang": "en",
        "created_at": "2020-07-20T21:11:02.000Z",
        "id": "1285321342938755074",
        "geo": {
            "place_id": "0a7dc9891a02c366"
        },
        "author_id": "42289581"
    },
    {
        "public_metrics": {
            "retweet_count": 0,
            "reply_count": 0,
            "like_count": 0,
            "quote_count": 0
        },
        "text": "If you are in Atlanta!! Stop by and check out my Frat Bro @jthebarberatl and his #FunnelCakeFridays. Located in West Midtown. DJ, Bar.. from 6-9 pm tonight!! I might roll my old behind out tonight \ud83e\udd37\ud83c\udffe\u200d\u2642\ufe0f https://t.co/A8QfCI6Sw3",
        "edit_history_tweet_ids": [
            "1281603789141741576"
        ],
        "lang": "en",
        "created_at": "2020-07-10T14:58:49.000Z",
        "id": "1281603789141741576",
        "geo": {
            "place_id": "2aacaaae6a17755c"
        },
        "author_id": "3385372334"
    },
    {
        "public_metrics": {
            "retweet_count": 0,
            "reply_count": 0,
            "like_count": 4,
            "quote_count": 0
        },
        "text": "It's Time. To. Close. The. City. \nExecutive tip toeing doesn't work. \nThere's no reason any bar or restaurant or gym \"need\" to be open . https://t.co/xKSHI1RxKq",
        "edit_history_tweet_ids": [
            "1281219489909157889"
        ],
        "lang": "en",
        "created_at": "2020-07-09T13:31:44.000Z",
        "id": "1281219489909157889",
        "geo": {
            "place_id": "2aacaaae6a17755c"
        },
        "author_id": "3385372334"
    },
    {
        "public_metrics": {
            "retweet_count": 0,
            "reply_count": 1,
            "like_count": 0,
            "quote_count": 1
        },
        "text": "Benzino got a restaurant in South DeKalb mall? Where the fuck i been",
        "edit_history_tweet_ids": [
            "1278423889056542726"
        ],
        "lang": "en",
        "created_at": "2020-07-01T20:23:01.000Z",
        "id": "1278423889056542726",
        "geo": {
            "place_id": "107c6dc5a9547000"
        },
        "author_id": "46388651"
    },
    {
        "public_metrics": {
            "retweet_count": 2,
            "reply_count": 1,
            "like_count": 20,
            "quote_count": 1
        },
        "text": "Oh yeah did I mention I own and operate my own juice bar and gym??? https://t.co/CmzVni3XOR",
        "edit_history_tweet_ids": [
            "1278385838078988288"
        ],
        "lang": "en",
        "created_at": "2020-07-01T17:51:49.000Z",
        "id": "1278385838078988288",
        "geo": {
            "place_id": "0a7dc9891a02c366"
        },
        "author_id": "1134589955651641346"
    },
    {
        "public_metrics": {
            "retweet_count": 2,
            "reply_count": 1,
            "like_count": 8,
            "quote_count": 2
        },
        "text": "Y\u2019all want a how-to video on how I make my Red Velvet Cinnamon Rolls? #baker #BlackOwnedBusiness #atlanta #bakery",
        "edit_history_tweet_ids": [
            "1276589774892081152"
        ],
        "lang": "en",
        "created_at": "2020-06-26T18:54:54.000Z",
        "id": "1276589774892081152",
        "geo": {
            "place_id": "0a7dc9891a02c366"
        },
        "author_id": "1275936115384553472"
    },
    {
        "public_metrics": {
            "retweet_count": 3,
            "reply_count": 0,
            "like_count": 17,
            "quote_count": 0
        },
        "text": "Just giving y\u2019all insight to what I\u2019m doing yes I\u2019m a personal trainer yes I am building my own gym and juice bar...... https://t.co/UVl03TIz04",
        "edit_history_tweet_ids": [
            "1275547914039853057"
        ],
        "lang": "en",
        "created_at": "2020-06-23T21:54:55.000Z",
        "id": "1275547914039853057",
        "geo": {
            "place_id": "0a7dc9891a02c366"
        },
        "author_id": "1134589955651641346"
    },
    {
        "public_metrics": {
            "retweet_count": 0,
            "reply_count": 0,
            "like_count": 0,
            "quote_count": 0
        },
        "text": "@TamKeshelle Yes honey. Scared the whole Thai restaurant",
        "edit_history_tweet_ids": [
            "1273608733684359168"
        ],
        "lang": "en",
        "created_at": "2020-06-18T13:29:19.000Z",
        "id": "1273608733684359168",
        "geo": {
            "place_id": "2aacaaae6a17755c"
        },
        "author_id": "3385372334"
    },
    {
        "public_metrics": {
            "retweet_count": 0,
            "reply_count": 1,
            "like_count": 0,
            "quote_count": 0
        },
        "text": "Before yall go to a restaurant do yall look at the menu online first so when get there you know what you want.",
        "edit_history_tweet_ids": [
            "1271270959186616320"
        ],
        "lang": "en",
        "created_at": "2020-06-12T02:39:50.000Z",
        "id": "1271270959186616320",
        "geo": {
            "place_id": "2aacaaae6a17755c"
        },
        "author_id": "467137141"
    },
    {
        "public_metrics": {
            "retweet_count": 1,
            "reply_count": 0,
            "like_count": 0,
            "quote_count": 0
        },
        "text": "Wish I was in a restaurant with a margarita \ud83d\ude14\ud83d\ude14\ud83d\ude14",
        "edit_history_tweet_ids": [
            "1269369479248490496"
        ],
        "lang": "en",
        "created_at": "2020-06-06T20:44:02.000Z",
        "id": "1269369479248490496",
        "geo": {
            "place_id": "2aacaaae6a17755c"
        },
        "author_id": "34947817"
    },
    {
        "public_metrics": {
            "retweet_count": 0,
            "reply_count": 0,
            "like_count": 0,
            "quote_count": 0
        },
        "text": "Was laying low tryna study for the Bar Exam shit is hell.",
        "edit_history_tweet_ids": [
            "1267545343610228736"
        ],
        "lang": "en",
        "created_at": "2020-06-01T19:55:34.000Z",
        "id": "1267545343610228736",
        "geo": {
            "place_id": "2aacaaae6a17755c"
        },
        "author_id": "467137141"
    },
    {
        "public_metrics": {
            "retweet_count": 0,
            "reply_count": 0,
            "like_count": 4,
            "quote_count": 0
        },
        "text": "@therealelp Great to see your working on that menu for the RTJ Restaurant franchise.",
        "edit_history_tweet_ids": [
            "1264333555280367616"
        ],
        "lang": "en",
        "created_at": "2020-05-23T23:13:04.000Z",
        "id": "1264333555280367616",
        "geo": {
            "place_id": "2aacaaae6a17755c"
        },
        "author_id": "20320547"
    },
    {
        "public_metrics": {
            "retweet_count": 0,
            "reply_count": 0,
            "like_count": 0,
            "quote_count": 0
        },
        "text": "Damn remember the days when you can just be at a bar, hugging people, go to the movie theater without a worry.",
        "edit_history_tweet_ids": [
            "1261462225224708097"
        ],
        "lang": "en",
        "created_at": "2020-05-16T01:03:25.000Z",
        "id": "1261462225224708097",
        "geo": {
            "place_id": "2aacaaae6a17755c"
        },
        "author_id": "209805280"
    },
    {
        "public_metrics": {
            "retweet_count": 0,
            "reply_count": 0,
            "like_count": 0,
            "quote_count": 0
        },
        "text": "Bar too high nights can\u2019t even reach it",
        "edit_history_tweet_ids": [
            "1261062195984707586"
        ],
        "lang": "en",
        "created_at": "2020-05-14T22:33:51.000Z",
        "id": "1261062195984707586",
        "geo": {
            "place_id": "0a7dc9891a02c366"
        },
        "author_id": "244663691"
    },
    {
        "public_metrics": {
            "retweet_count": 0,
            "reply_count": 0,
            "like_count": 0,
            "quote_count": 0
        },
        "text": "@MavenofHonor Conan O\u2019Brien was the first celebrity I served in the restaurant industry. He kind of ruined every celeb after. He actually remembered my name, asked me questions about myself, and as the rest of the crew was leaving, separated to come find me and that me.",
        "edit_history_tweet_ids": [
            "1260938870860001282"
        ],
        "lang": "en",
        "created_at": "2020-05-14T14:23:48.000Z",
        "id": "1260938870860001282",
        "geo": {
            "place_id": "2aacaaae6a17755c"
        },
        "author_id": "12622482"
    },
    {
        "public_metrics": {
            "retweet_count": 3,
            "reply_count": 1,
            "like_count": 7,
            "quote_count": 0
        },
        "text": "Turning your crib into a restaurant creating your own personal menu is def a dope date idea whenever the time is right I\u2019m running that back again",
        "edit_history_tweet_ids": [
            "1255480357635477508"
        ],
        "lang": "en",
        "created_at": "2020-04-29T12:53:37.000Z",
        "id": "1255480357635477508",
        "geo": {
            "place_id": "0a7dc9891a02c366"
        },
        "author_id": "225513508"
    },
    {
        "public_metrics": {
            "retweet_count": 1,
            "reply_count": 3,
            "like_count": 21,
            "quote_count": 0
        },
        "text": "@lolhydtho @checktherhyme1 @AllLoveHipHop Really.. whats your favorite Missy bar? And whats your top 5 deep cuts from MC Lyte?",
        "edit_history_tweet_ids": [
            "1248490411930177538"
        ],
        "lang": "en",
        "created_at": "2020-04-10T05:58:04.000Z",
        "id": "1248490411930177538",
        "geo": {
            "place_id": "2aacaaae6a17755c"
        },
        "author_id": "158572857"
    },
    {
        "public_metrics": {
            "retweet_count": 0,
            "reply_count": 1,
            "like_count": 2,
            "quote_count": 0
        },
        "text": "\u201cWhat\u2019s your favorite Missy Bar??\u201d Niggas say stupid shit like: Put my thing down flip it and reverse it.. Ti esrever dna ti pilf, nwod gniht ym tup \ud83d\ude02\ud83d\ude02 Missy is not a lyricist",
        "edit_history_tweet_ids": [
            "1245692785786785793"
        ],
        "lang": "en",
        "created_at": "2020-04-02T12:41:18.000Z",
        "id": "1245692785786785793",
        "geo": {
            "place_id": "2aacaaae6a17755c"
        },
        "author_id": "158572857"
    },
    {
        "public_metrics": {
            "retweet_count": 0,
            "reply_count": 1,
            "like_count": 0,
            "quote_count": 0
        },
        "text": "@ohsofineky Lmaoooo I\u2019ll just go to restaurant 10 or red pepper",
        "edit_history_tweet_ids": [
            "1245463374814683140"
        ],
        "lang": "en",
        "created_at": "2020-04-01T21:29:42.000Z",
        "id": "1245463374814683140",
        "geo": {
            "place_id": "0a7dc9891a02c366"
        },
        "author_id": "2150192717"
    },
    {
        "public_metrics": {
            "retweet_count": 0,
            "reply_count": 1,
            "like_count": 1,
            "quote_count": 0
        },
        "text": "@smarticle_keem It\u2019s this one called five daughters bakery at Ponce city market. We got sublimes. Those are the two i tried. The other two i seen were duck donuts, vegan dream for the vegans. Happy donuts. Etc. but they\u2019re all in Atlanta, and it\u2019s others outside of Atlanta.",
        "edit_history_tweet_ids": [
            "1244692492064370689"
        ],
        "lang": "en",
        "created_at": "2020-03-30T18:26:30.000Z",
        "id": "1244692492064370689",
        "geo": {
            "place_id": "0a7dc9891a02c366"
        },
        "author_id": "2150192717"
    },
    {
        "public_metrics": {
            "retweet_count": 0,
            "reply_count": 0,
            "like_count": 1,
            "quote_count": 0
        },
        "text": "I just bought a gift card in support of Hattie B's Hot Chicken - Atlanta. Join me in supporting the restaurant community by paying it forward.\n#RallyForRestaurants https://t.co/3EXH2mVXQN",
        "edit_history_tweet_ids": [
            "1240434320696901632"
        ],
        "lang": "en",
        "created_at": "2020-03-19T00:26:02.000Z",
        "id": "1240434320696901632",
        "geo": {
            "place_id": "2aacaaae6a17755c"
        },
        "author_id": "425364395"
    },
    {
        "public_metrics": {
            "retweet_count": 0,
            "reply_count": 0,
            "like_count": 1,
            "quote_count": 0
        },
        "text": "Come get a drink and a dance ... safe distances and turnup \ud83d\udcb8\ud83d\udcb8\ud83d\udcb8\ud83e\udd37\ud83c\udffc\u200d\u2640\ufe0f\ud83e\udd37\ud83c\udffc\u200d\u2640\ufe0f\ud83e\udd37\ud83c\udffc\u200d\u2640\ufe0f\ud83d\udc8b\ud83d\udc8b\ud83d\udc8bthe bar is open \ud83e\udd43\ud83e\udd43\ud83e\udd43\ud83d\udcb8\ud83d\udcb8\ud83d\udcb8\ud83d\ude80\ud83d\ude80\ud83d\ude80 \u30fb\u30fb\u30fb\nOn the 1s and 2s at The Office \u30fb\u30fb\u30fbplus my new album Sixxleigh streaming now \ud83d\udc96\ud83d\udc96\ud83d\udc96\u2026 https://t.co/xkXa0Pdd0n",
        "edit_history_tweet_ids": [
            "1240140836165296130"
        ],
        "geo": {
            "coordinates": {
                "type": "Point",
                "coordinates": [
                    -84.34983187,
                    33.70949858
                ]
            },
            "place_id": "8173485c72e78ca5"
        },
        "lang": "en",
        "created_at": "2020-03-18T04:59:50.000Z",
        "id": "1240140836165296130",
        "author_id": "19300834"
    },
    {
        "public_metrics": {
            "retweet_count": 0,
            "reply_count": 0,
            "like_count": 0,
            "quote_count": 0
        },
        "text": "The bar is open  come get a dance \ud83e\udd43\ud83e\udd43\ud83e\udd43\ud83d\udcb8\ud83d\udcb8\ud83d\udcb8\ud83d\ude80\ud83d\ude80\ud83d\ude80 \u30fb\u30fb\u30fb\nOn the 1s and 2s at The Office \u30fb\u30fb\u30fbplus my new album Sixxleigh streaming now \ud83d\udc96\ud83d\udc96\ud83d\udc96 #thesingerthatturnsuptoo\n\ud83d\ude4c\ud83c\udffc\ud83d\ude80\ud83d\ude80\nSinger songwriter dj \ud83d\ude0b\ud83d\ude0b\ud83d\ude0b\n\ud83d\udcb8\ud83d\udcb8\ud83d\udcb8\nI\u2019m on the 1s and 2s wit the\u2026 https://t.co/9mcjbGECn6",
        "edit_history_tweet_ids": [
            "1240135982667661312"
        ],
        "geo": {
            "coordinates": {
                "type": "Point",
                "coordinates": [
                    -84.34983187,
                    33.70949858
                ]
            },
            "place_id": "8173485c72e78ca5"
        },
        "lang": "en",
        "created_at": "2020-03-18T04:40:33.000Z",
        "id": "1240135982667661312",
        "author_id": "19300834"
    },
    {
        "public_metrics": {
            "retweet_count": 0,
            "reply_count": 0,
            "like_count": 1,
            "quote_count": 0
        },
        "text": "I\u2019m giving Air hugs and bar is open \ud83d\ude43\ud83d\ude43\ud83d\ude43 \ud83e\udd43\ud83e\udd43\ud83e\udd43\ud83d\udcb8\ud83d\udcb8\ud83d\udcb8\ud83d\ude80\ud83d\ude80\ud83d\ude80 \u30fb\u30fb\u30fb\nOn the 1s and 2s at The Office \u30fb\u30fb\u30fbplus my new album Sixxleigh streaming now \ud83d\udc96\ud83d\udc96\ud83d\udc96 #thesingerthatturnsuptoo\n\ud83d\ude4c\ud83c\udffc\ud83d\ude80\ud83d\ude80\nSinger songwriter dj \ud83d\ude0b\ud83d\ude0b\ud83d\ude0b\n\ud83d\udcb8\ud83d\udcb8\ud83d\udcb8\nI\u2019m on the 1s and 2s\u2026 https://t.co/Pi7ZOuF6mN",
        "edit_history_tweet_ids": [
            "1240133785095745547"
        ],
        "geo": {
            "coordinates": {
                "type": "Point",
                "coordinates": [
                    -84.34983187,
                    33.70949858
                ]
            },
            "place_id": "8173485c72e78ca5"
        },
        "lang": "en",
        "created_at": "2020-03-18T04:31:49.000Z",
        "id": "1240133785095745547",
        "author_id": "19300834"
    },
    {
        "public_metrics": {
            "retweet_count": 0,
            "reply_count": 0,
            "like_count": 0,
            "quote_count": 0
        },
        "text": "the bar is open \ud83e\udd43\ud83e\udd43\ud83e\udd43\ud83d\udcb8\ud83d\udcb8\ud83d\udcb8\ud83d\ude80\ud83d\ude80\ud83d\ude80 \u30fb\u30fb\u30fb\nOn the 1s and 2s at The Office \u30fb\u30fb\u30fbplus my new album Sixxleigh streaming now \ud83d\udc96\ud83d\udc96\ud83d\udc96 #thesingerthatturnsuptoo\n\ud83d\ude4c\ud83c\udffc\ud83d\ude80\ud83d\ude80\nSinger songwriter dj \ud83d\ude0b\ud83d\ude0b\ud83d\ude0b\n\ud83d\udcb8\ud83d\udcb8\ud83d\udcb8\nI\u2019m on the 1s and 2s wit the sexy ladies at\u2026 https://t.co/cqnpLEbzGU",
        "edit_history_tweet_ids": [
            "1240132278833086465"
        ],
        "geo": {
            "coordinates": {
                "type": "Point",
                "coordinates": [
                    -84.34983187,
                    33.70949858
                ]
            },
            "place_id": "8173485c72e78ca5"
        },
        "lang": "en",
        "created_at": "2020-03-18T04:25:50.000Z",
        "id": "1240132278833086465",
        "author_id": "19300834"
    },
    {
        "public_metrics": {
            "retweet_count": 0,
            "reply_count": 0,
            "like_count": 0,
            "quote_count": 0
        },
        "text": "\ud83d\ude0b\ud83d\ude0b\ud83d\ude0b\nHugs on hold but the bar is open \ud83e\udd43\ud83e\udd43\ud83e\udd43\ud83d\udcb8\ud83d\udcb8\ud83d\udcb8\ud83d\ude80\ud83d\ude80\ud83d\ude80 \u30fb\u30fb\u30fb\nOn the 1s and 2s at The Office \u30fb\u30fb\u30fbplus my new album Sixxleigh streaming now \ud83d\udc96\ud83d\udc96\ud83d\udc96 #thesingerthatturnsuptoo\n\ud83d\ude4c\ud83c\udffc\ud83d\ude80\ud83d\ude80\nSinger songwriter dj \ud83d\ude0b\ud83d\ude0b\ud83d\ude0b\n\ud83d\udcb8\ud83d\udcb8\ud83d\udcb8\nI\u2019m on the 1s and 2s wit\u2026 https://t.co/6J3JqUiFuN",
        "edit_history_tweet_ids": [
            "1240131332816199686"
        ],
        "geo": {
            "coordinates": {
                "type": "Point",
                "coordinates": [
                    -84.34983187,
                    33.70949858
                ]
            },
            "place_id": "8173485c72e78ca5"
        },
        "lang": "en",
        "created_at": "2020-03-18T04:22:04.000Z",
        "id": "1240131332816199686",
        "author_id": "19300834"
    },
    {
        "public_metrics": {
            "retweet_count": 0,
            "reply_count": 0,
            "like_count": 0,
            "quote_count": 0
        },
        "text": "Hugs on hold but the bar is open \ud83e\udd43\ud83e\udd43\ud83e\udd43\ud83d\udcb8\ud83d\udcb8\ud83d\udcb8\ud83d\ude80\ud83d\ude80\ud83d\ude80 \n\u30fb\u30fb\u30fb\nOn the 1s and 2s at The Office \u30fb\u30fb\u30fbplus my new album Sixxleigh streaming now \ud83d\udc96\ud83d\udc96\ud83d\udc96 #thesingerthatturnsuptoo\n\ud83d\ude4c\ud83c\udffc\ud83d\ude80\ud83d\ude80\nSinger songwriter dj \ud83d\ude0b\ud83d\ude0b\ud83d\ude0b\n\ud83d\udcb8\ud83d\udcb8\ud83d\udcb8\nI\u2019m on the 1s and 2s wit the\u2026 https://t.co/AESNZ11jEB",
        "edit_history_tweet_ids": [
            "1240096694638915585"
        ],
        "geo": {
            "coordinates": {
                "type": "Point",
                "coordinates": [
                    -84.34983187,
                    33.70949858
                ]
            },
            "place_id": "8173485c72e78ca5"
        },
        "lang": "en",
        "created_at": "2020-03-18T02:04:26.000Z",
        "id": "1240096694638915585",
        "author_id": "19300834"
    },
    {
        "public_metrics": {
            "retweet_count": 0,
            "reply_count": 0,
            "like_count": 0,
            "quote_count": 0
        },
        "text": "Hulk ...............  smash @ Phat Phish Cafe LLC https://t.co/5OO91kLb9L",
        "edit_history_tweet_ids": [
            "1237870841125195776"
        ],
        "geo": {
            "coordinates": {
                "type": "Point",
                "coordinates": [
                    -84.32261,
                    33.72554
                ]
            },
            "place_id": "8173485c72e78ca5"
        },
        "lang": "en",
        "created_at": "2020-03-11T22:39:41.000Z",
        "id": "1237870841125195776",
        "author_id": "100600738"
    },
    {
        "public_metrics": {
            "retweet_count": 6,
            "reply_count": 0,
            "like_count": 7,
            "quote_count": 0
        },
        "text": "One of the customers who was grazed at Checkers Restaurant  talks about the horrifying ordeal only on Fox5.  @FOX5Atlanta https://t.co/3H4U7CtM3f",
        "edit_history_tweet_ids": [
            "1235614643852324866"
        ],
        "lang": "en",
        "created_at": "2020-03-05T17:14:22.000Z",
        "id": "1235614643852324866",
        "geo": {
            "place_id": "0a7dc9891a02c366"
        },
        "author_id": "334692748"
    },
    {
        "public_metrics": {
            "retweet_count": 0,
            "reply_count": 2,
            "like_count": 0,
            "quote_count": 0
        },
        "text": "We walked from CAU to Museum Bar one time in 2013... the LAST time I was pressed for a play. We was so wild",
        "edit_history_tweet_ids": [
            "1234340611341324288"
        ],
        "lang": "en",
        "created_at": "2020-03-02T04:51:49.000Z",
        "id": "1234340611341324288",
        "geo": {
            "place_id": "2aacaaae6a17755c"
        },
        "author_id": "158572857"
    },
    {
        "public_metrics": {
            "retweet_count": 0,
            "reply_count": 1,
            "like_count": 8,
            "quote_count": 2
        },
        "text": "this flyer shit getting out of hand lol Our Bar ATL grand opening week artwork all me. no thanks required just pull up &amp; tip the bartenders",
        "edit_history_tweet_ids": [
            "1232447439723847682"
        ],
        "lang": "en",
        "created_at": "2020-02-25T23:29:02.000Z",
        "id": "1232447439723847682",
        "geo": {
            "place_id": "0a7dc9891a02c366"
        },
        "author_id": "175572207"
    },
    {
        "public_metrics": {
            "retweet_count": 0,
            "reply_count": 0,
            "like_count": 0,
            "quote_count": 0
        },
        "text": "I'm at China Chef Cafe in Atlanta, GA https://t.co/BoZNABJBMA",
        "edit_history_tweet_ids": [
            "1232365774980943872"
        ],
        "geo": {
            "coordinates": {
                "type": "Point",
                "coordinates": [
                    -84.349621,
                    33.714036
                ]
            },
            "place_id": "8173485c72e78ca5"
        },
        "lang": "en",
        "created_at": "2020-02-25T18:04:31.000Z",
        "id": "1232365774980943872",
        "author_id": "1481137530"
    },
    {
        "public_metrics": {
            "retweet_count": 0,
            "reply_count": 0,
            "like_count": 0,
            "quote_count": 0
        },
        "text": "I'm at It\u2019s A Wrap Cafe in Atlanta, GA https://t.co/RyhtsebyHg",
        "edit_history_tweet_ids": [
            "1232363163728928768"
        ],
        "geo": {
            "coordinates": {
                "type": "Point",
                "coordinates": [
                    -84.350062,
                    33.716256
                ]
            },
            "place_id": "8173485c72e78ca5"
        },
        "lang": "en",
        "created_at": "2020-02-25T17:54:09.000Z",
        "id": "1232363163728928768",
        "author_id": "1481137530"
    },
    {
        "public_metrics": {
            "retweet_count": 0,
            "reply_count": 2,
            "like_count": 0,
            "quote_count": 0
        },
        "text": "@tim2flyaguy Whew. A whole lot. Bar Nights, demos, community service, and various events.",
        "edit_history_tweet_ids": [
            "1231080836021280769"
        ],
        "lang": "en",
        "created_at": "2020-02-22T04:58:38.000Z",
        "id": "1231080836021280769",
        "geo": {
            "place_id": "0a7dc9891a02c366"
        },
        "author_id": "42289581"
    },
    {
        "public_metrics": {
            "retweet_count": 1,
            "reply_count": 1,
            "like_count": 3,
            "quote_count": 1
        },
        "text": ".\n.\n.\n.\n.\n#calirap #freestyle #seat #londonlife #soulmates #undergroundhiphop #bars #barz #rapmusic #foodandwine #gymnast #cocktailbar #rapping #bar #music #london #rappers #foodphotography #emcee #bouncemusic  #lahairstylist ##hiphop #freestylefriday #rapper #love #rap https://t.co/3rBMdwni6E",
        "edit_history_tweet_ids": [
            "1230981307511037953"
        ],
        "lang": "und",
        "created_at": "2020-02-21T22:23:08.000Z",
        "id": "1230981307511037953",
        "geo": {
            "place_id": "0a7dc9891a02c366"
        },
        "author_id": "110323298"
    },
    {
        "public_metrics": {
            "retweet_count": 0,
            "reply_count": 1,
            "like_count": 0,
            "quote_count": 0
        },
        "text": "this you at the bar lol https://t.co/mOssd5TL0F https://t.co/0D4x7YvHuy",
        "edit_history_tweet_ids": [
            "1230643221220462592"
        ],
        "lang": "en",
        "created_at": "2020-02-20T23:59:42.000Z",
        "id": "1230643221220462592",
        "geo": {
            "place_id": "0a7dc9891a02c366"
        },
        "author_id": "175572207"
    },
    {
        "public_metrics": {
            "retweet_count": 0,
            "reply_count": 0,
            "like_count": 0,
            "quote_count": 0
        },
        "text": "Time to dance @ Bigelow's Bar &amp; Grill https://t.co/qCTnrMXt3S",
        "edit_history_tweet_ids": [
            "1230364893980708864"
        ],
        "geo": {
            "coordinates": {
                "type": "Point",
                "coordinates": [
                    -84.30996126,
                    33.71328619
                ]
            },
            "place_id": "2aacaaae6a17755c"
        },
        "lang": "en",
        "created_at": "2020-02-20T05:33:44.000Z",
        "id": "1230364893980708864",
        "author_id": "1125376592"
    },
    {
        "public_metrics": {
            "retweet_count": 0,
            "reply_count": 0,
            "like_count": 0,
            "quote_count": 0
        },
        "text": "I want to try this restaurant but don't want to go by myself.",
        "edit_history_tweet_ids": [
            "1223656679474110467"
        ],
        "lang": "en",
        "created_at": "2020-02-01T17:17:41.000Z",
        "id": "1223656679474110467",
        "geo": {
            "place_id": "2aacaaae6a17755c"
        },
        "author_id": "467137141"
    },
    {
        "public_metrics": {
            "retweet_count": 0,
            "reply_count": 0,
            "like_count": 0,
            "quote_count": 0
        },
        "text": "itsawrapcafe thanks for letting me come by and check out your wraps make sure to grab a nice ice cold beeccentriklemonade with your next order!!! @ It's A Wrap Cafe https://t.co/7KuYn5vo0s",
        "edit_history_tweet_ids": [
            "1222667348324364297"
        ],
        "geo": {
            "coordinates": {
                "type": "Point",
                "coordinates": [
                    -84.35002,
                    33.7161
                ]
            },
            "place_id": "8173485c72e78ca5"
        },
        "lang": "en",
        "created_at": "2020-01-29T23:46:26.000Z",
        "id": "1222667348324364297",
        "author_id": "213011248"
    },
    {
        "public_metrics": {
            "retweet_count": 0,
            "reply_count": 0,
            "like_count": 5,
            "quote_count": 0
        },
        "text": "Just to be clear, this was only a question to get opinions. I never expect anything from a server except for good service. I am not one to ever send my food back or complain at a restaurant. https://t.co/zHRZgKlQsC",
        "edit_history_tweet_ids": [
            "1221609133847261187"
        ],
        "lang": "en",
        "created_at": "2020-01-27T01:41:28.000Z",
        "id": "1221609133847261187",
        "geo": {
            "place_id": "0a7dc9891a02c366"
        },
        "author_id": "27966820"
    },
    {
        "public_metrics": {
            "retweet_count": 0,
            "reply_count": 0,
            "like_count": 0,
            "quote_count": 0
        },
        "text": "We done had a blast with unk and Ava\u203c @ Bigelow's Bar &amp; Grill https://t.co/vfhsblG1Rj",
        "edit_history_tweet_ids": [
            "1219823452577783808"
        ],
        "geo": {
            "coordinates": {
                "type": "Point",
                "coordinates": [
                    -84.30996126,
                    33.71328619
                ]
            },
            "place_id": "2aacaaae6a17755c"
        },
        "lang": "en",
        "created_at": "2020-01-22T03:25:48.000Z",
        "id": "1219823452577783808",
        "author_id": "208683417"
    },
    {
        "public_metrics": {
            "retweet_count": 0,
            "reply_count": 0,
            "like_count": 0,
            "quote_count": 0
        },
        "text": "Always good to see my bro @eurogotit and the whole authenticempiremg out doing they thang!!! ghost_bar_atlanta cutdaredtapentparties @ Now or Never Music Group https://t.co/h24ydMWlKW",
        "edit_history_tweet_ids": [
            "1218451596809506816"
        ],
        "geo": {
            "coordinates": {
                "type": "Point",
                "coordinates": [
                    -84.2989948,
                    33.6949583
                ]
            },
            "place_id": "0a7dc9891a02c366"
        },
        "lang": "en",
        "created_at": "2020-01-18T08:34:33.000Z",
        "id": "1218451596809506816",
        "author_id": "54447276"
    },
    {
        "public_metrics": {
            "retweet_count": 0,
            "reply_count": 0,
            "like_count": 1,
            "quote_count": 0
        },
        "text": "At a bar on a Wednesday at 12:40am  ... I need to re-evaluate my life",
        "edit_history_tweet_ids": [
            "1215146362314149889"
        ],
        "lang": "en",
        "created_at": "2020-01-09T05:40:43.000Z",
        "id": "1215146362314149889",
        "geo": {
            "place_id": "0a7dc9891a02c366"
        },
        "author_id": "260070034"
    },
    {
        "public_metrics": {
            "retweet_count": 3,
            "reply_count": 1,
            "like_count": 6,
            "quote_count": 0
        },
        "text": "i need people who wanna study with me and go to the cafe at ungodly hours of the night \ud83d\ude02 https://t.co/UrDbjC5Pa7",
        "edit_history_tweet_ids": [
            "1213490024253214722"
        ],
        "lang": "en",
        "created_at": "2020-01-04T15:59:01.000Z",
        "id": "1213490024253214722",
        "geo": {
            "place_id": "2aacaaae6a17755c"
        },
        "author_id": "2306034177"
    }
]